Workbook

Sheet Transactions
A1: ID | B1: Name | C1: Amount | D1: Type | E1: Created At | F1: Updated At | G1: Description | H1: Account | I1: Category | J1: From Account | K1: To Account | L1: Person | M1: Recurring | N1: User | O1: Account UUID | P1: Category UUID | Q1: From Account UUID | R1: To Account UUID | S1: Person UUID | T1: Recurring UUID | U1: User UUID
A2: 1 | B2: Initial balance | C2: 2000 | D2: Income | E2: 2026-07-04T00:25:08.274 | F2: 2026-07-04T00:25:08.274 | H2: =IF(O2="","",IFERROR(INDEX(Accounts!$B$2:$B$24,MATCH(O2,Accounts!$A$2:$A$24,0)),"Unknown")) | I2: =IF(P2="","",IFERROR(INDEX(Categories!$B$2:$B$25,MATCH(P2,Categories!$A$2:$A$25,0)),"Unknown")) | J2: =IF(Q2="","",IFERROR(INDEX(Accounts!$B$2:$B$24,MATCH(Q2,Accounts!$A$2:$A$24,0)),"Unknown")) | K2: =IF(R2="","",IFERROR(INDEX(Accounts!$B$2:$B$24,MATCH(R2,Accounts!$A$2:$A$24,0)),"Unknown")) | L2: =IF(S2="","",IFERROR(INDEX(People!$B$2:$B$7,MATCH(S2,People!$A$2:$A$7,0)),"Unknown")) | M2: =IF(T2="","",IFERROR(INDEX(Recurrings!$B$2:$B$3,MATCH(T2,Recurrings!$A$2:$A$3,0)),"Unknown")) | N2: =IF(U2="","",IFERROR(INDEX(Users!$B$2:$B$2,MATCH(U2,Users!$A$2:$A$2,0)),"Unknown")) | O2: 07510728-f320-4be7-b92d-39526c02e73d | P2: 1c612037-9067-4e69-aebc-14619b77b363 | U2: 814248de-0f8d-4712-bd00-91d12164a414
A3: 2 | B3: Initial balance | C3: 2000 | D3: Income | E3: 2026-07-01T00:25:36.000 | F3: 2026-07-04T00:28:50.516 | H3: =IF(O3="","",IFERROR(INDEX(Accounts!$B$2:$B$24,MATCH(O3,Accounts!$A$2:$A$24,0)),"Unknown")) | I3: =IF(P3="","",IFERROR(INDEX(Categories!$B$2:$B$25,MATCH(P3,Categories!$A$2:$A$25,0)),"Unknown")) | J3: =IF(Q3="","",IFERROR(INDEX(Accounts!$B$2:$B$24,MATCH(Q3,Accounts!$A$2:$A$24,0)),"Unknown")) | K3: =IF(R3="","",IFERROR(INDEX(Accounts!$B$2:$B$24,MATCH(R3,Accounts!$A$2:$A$24,0)),"Unknown")) | L3: =IF(S3="","",IFERROR(INDEX(People!$B$2:$B$7,MATCH(S3,People!$A$2:$A$7,0)),"Unknown")) | M3: =IF(T3="","",IFERROR(INDEX(Recurrings!$B$2:$B$3,MATCH(T3,Recurrings!$A$2:$A$3,0)),"Unknown")) | N3: =IF(U3="","",IFERROR(INDEX(Users!$B$2:$B$2,MATCH(U3,Users!$A$2:$A$2,0)),"Unknown")) | O3: e4446497-b2a1-4493-a796-44893af13f78 | P3: 1c612037-9067-4e69-aebc-14619b77b363 | U3: 814248de-0f8d-4712-bd00-91d12164a414
A4: 3 | B4: Monthly credit | C4: 4000 | D4: Transfer | E4: 2026-07-01T00:26:51.000 | F4: 2026-07-26T02:46:53.697 | H4: =IF(O4="","",IFERROR(INDEX(Accounts!$B$2:$B$24,MATCH(O4,Accounts!$A$2:$A$24,0)),"Unknown")) | I4: =IF(P4="","",IFERROR(INDEX(Categories!$B$2:$B$25,MATCH(P4,Categories!$A$2:$A$25,0)),"Unknown")) | J4: =IF(Q4="","",IFERROR(INDEX(Accounts!$B$2:$B$24,MATCH(Q4,Accounts!$A$2:$A$24,0)),"Unknown")) | K4: =IF(R4="","",IFERROR(INDEX(Accounts!$B$2:$B$24,MATCH(R4,Accounts!$A$2:$A$24,0)),"Unknown")) | L4: =IF(S4="","",IFERROR(INDEX(People!$B$2:$B$7,MATCH(S4,People!$A$2:$A$7,0)),"Unknown")) | M4: =IF(T4="","",IFERROR(INDEX(Recurrings!$B$2:$B$3,MATCH(T4,Recurrings!$A$2:$A$3,0)),"Unknown")) | N4: =IF(U4="","",IFERROR(INDEX(Users!$B$2:$B$2,MATCH(U4,Users!$A$2:$A$2,0)),"Unknown")) | Q4: 183283c7-9ae3-49e4-ae84-a5364bc337ea | R4: 18110823-8fe5-4547-b1d3-8dbd2cc5b2e3 | S4: 7214a9a0-5619-49f8-8521-181d4faf1190 | U4: 814248de-0f8d-4712-bd00-91d12164a414
A5: 4 | B5: Food | C5: 200 | D5: Expense | E5: 2026-07-04T00:30:18.916 | F5: 2026-07-04T00:30:18.916 | H5: =IF(O5="","",IFERROR(INDEX(Accounts!$B$2:$B$24,MATCH(O5,Accounts!$A$2:$A$24,0)),"Unknown")) | I5: =IF(P5="","",IFERROR(INDEX(Categories!$B$2:$B$25,MATCH(P5,Categories!$A$2:$A$25,0)),"Unknown")) | J5: =IF(Q5="","",IFERROR(INDEX(Accounts!$B$2:$B$24,MATCH(Q5,Accounts!$A$2:$A$24,0)),"Unknown")) | K5: =IF(R5="","",IFERROR(INDEX(Accounts!$B$2:$B$24,MATCH(R5,Accounts!$A$2:$A$24,0)),"Unknown")) | L5: =IF(S5="","",IFERROR(INDEX(People!$B$2:$B$7,MATCH(S5,People!$A$2:$A$7,0)),"Unknown")) | M5: =IF(T5="","",IFERROR(INDEX(Recurrings!$B$2:$B$3,MATCH(T5,Recurrings!$A$2:$A$3,0)),"Unknown")) | N5: =IF(U5="","",IFERROR(INDEX(Users!$B$2:$B$2,MATCH(U5,Users!$A$2:$A$2,0)),"Unknown")) | O5: a5b44f57-40f5-4b0e-96db-1179f20d75d0 | P5: 9ea0a2b1-4b22-40a4-81ab-843452f9c274 | U5: 814248de-0f8d-4712-bd00-91d12164a414
A6: 5 | B6: Daily expenses | C6: 222 | D6: Expense | E6: 2026-07-02T00:30:26.000 | F6: 2026-08-01T02:04:32.575 | H6: =IF(O6="","",IFERROR(INDEX(Accounts!$B$2:$B$24,MATCH(O6,Accounts!$A$2:$A$24,0)),"Unknown")) | I6: =IF(P6="","",IFERROR(INDEX(Categories!$B$2:$B$25,MATCH(P6,Categories!$A$2:$A$25,0)),"Unknown")) | J6: =IF(Q6="","",IFERROR(INDEX(Accounts!$B$2:$B$24,MATCH(Q6,Accounts!$A$2:$A$24,0)),"Unknown")) | K6: =IF(R6="","",IFERROR(INDEX(Accounts!$B$2:$B$24,MATCH(R6,Accounts!$A$2:$A$24,0)),"Unknown")) | L6: =IF(S6="","",IFERROR(INDEX(People!$B$2:$B$7,MATCH(S6,People!$A$2:$A$7,0)),"Unknown")) | M6: =IF(T6="","",IFERROR(INDEX(Recurrings!$B$2:$B$3,MATCH(T6,Recurrings!$A$2:$A$3,0)),"Unknown")) | N6: =IF(U6="","",IFERROR(INDEX(Users!$B$2:$B$2,MATCH(U6,Users!$A$2:$A$2,0)),"Unknown")) | O6: a5b44f57-40f5-4b0e-96db-1179f20d75d0 | P6: b5eb22d9-3779-43fc-99af-eded3ff9bcd8 | U6: 814248de-0f8d-4712-bd00-91d12164a414
A7: 6 | B7: Arbind Saha checkup and meds | C7: 2710 | D7: Expense | E7: 2026-07-02T00:31:29.000 | F7: 2026-07-26T02:49:27.552 | H7: =IF(O7="","",IFERROR(INDEX(Accounts!$B$2:$B$24,MATCH(O7,Accounts!$A$2:$A$24,0)),"Unknown")) | I7: =IF(P7="","",IFERROR(INDEX(Categories!$B$2:$B$25,MATCH(P7,Categories!$A$2:$A$25,0)),"Unknown")) | J7: =IF(Q7="","",IFERROR(INDEX(Accounts!$B$2:$B$24,MATCH(Q7,Accounts!$A$2:$A$24,0)),"Unknown")) | K7: =IF(R7="","",IFERROR(INDEX(Accounts!$B$2:$B$24,MATCH(R7,Accounts!$A$2:$A$24,0)),"Unknown")) | L7: =IF(S7="","",IFERROR(INDEX(People!$B$2:$B$7,MATCH(S7,People!$A$2:$A$7,0)),"Unknown")) | M7: =IF(T7="","",IFERROR(INDEX(Recurrings!$B$2:$B$3,MATCH(T7,Recurrings!$A$2:$A$3,0)),"Unknown")) | N7: =IF(U7="","",IFERROR(INDEX(Users!$B$2:$B$2,MATCH(U7,Users!$A$2:$A$2,0)),"Unknown")) | O7: 183283c7-9ae3-49e4-ae84-a5364bc337ea | P7: 892419eb-083b-410f-b146-1f3c70914aa1 | S7: 7214a9a0-5619-49f8-8521-181d4faf1190 | U7: 814248de-0f8d-4712-bd00-91d12164a414
A8: 7 | B8: Expense | C8: 380 | D8: Expense | E8: 2026-07-03T00:32:26.000 | F8: 2026-07-26T02:49:32.885 | H8: =IF(O8="","",IFERROR(INDEX(Accounts!$B$2:$B$24,MATCH(O8,Accounts!$A$2:$A$24,0)),"Unknown")) | I8: =IF(P8="","",IFERROR(INDEX(Categories!$B$2:$B$25,MATCH(P8,Categories!$A$2:$A$25,0)),"Unknown")) | J8: =IF(Q8="","",IFERROR(INDEX(Accounts!$B$2:$B$24,MATCH(Q8,Accounts!$A$2:$A$24,0)),"Unknown")) | K8: =IF(R8="","",IFERROR(INDEX(Accounts!$B$2:$B$24,MATCH(R8,Accounts!$A$2:$A$24,0)),"Unknown")) | L8: =IF(S8="","",IFERROR(INDEX(People!$B$2:$B$7,MATCH(S8,People!$A$2:$A$7,0)),"Unknown")) | M8: =IF(T8="","",IFERROR(INDEX(Recurrings!$B$2:$B$3,MATCH(T8,Recurrings!$A$2:$A$3,0)),"Unknown")) | N8: =IF(U8="","",IFERROR(INDEX(Users!$B$2:$B$2,MATCH(U8,Users!$A$2:$A$2,0)),"Unknown")) | O8: 183283c7-9ae3-49e4-ae84-a5364bc337ea | P8: 892419eb-083b-410f-b146-1f3c70914aa1 | S8: 7214a9a0-5619-49f8-8521-181d4faf1190 | U8: 814248de-0f8d-4712-bd00-91d12164a414
A9: 8 | B9: Monthly credit | C9: 10000 | D9: Transfer | E9: 2026-07-01T00:34:30.000 | F9: 2026-07-26T02:48:12.466 | H9: =IF(O9="","",IFERROR(INDEX(Accounts!$B$2:$B$24,MATCH(O9,Accounts!$A$2:$A$24,0)),"Unknown")) | I9: =IF(P9="","",IFERROR(INDEX(Categories!$B$2:$B$25,MATCH(P9,Categories!$A$2:$A$25,0)),"Unknown")) | J9: =IF(Q9="","",IFERROR(INDEX(Accounts!$B$2:$B$24,MATCH(Q9,Accounts!$A$2:$A$24,0)),"Unknown")) | K9: =IF(R9="","",IFERROR(INDEX(Accounts!$B$2:$B$24,MATCH(R9,Accounts!$A$2:$A$24,0)),"Unknown")) | L9: =IF(S9="","",IFERROR(INDEX(People!$B$2:$B$7,MATCH(S9,People!$A$2:$A$7,0)),"Unknown")) | M9: =IF(T9="","",IFERROR(INDEX(Recurrings!$B$2:$B$3,MATCH(T9,Recurrings!$A$2:$A$3,0)),"Unknown")) | N9: =IF(U9="","",IFERROR(INDEX(Users!$B$2:$B$2,MATCH(U9,Users!$A$2:$A$2,0)),"Unknown")) | Q9: 183283c7-9ae3-49e4-ae84-a5364bc337ea | R9: 8cedd8c1-7bcb-4b94-be6b-e72b888f1084 | S9: 7214a9a0-5619-49f8-8521-181d4faf1190 | U9: 814248de-0f8d-4712-bd00-91d12164a414
A10: 9 | B10: Arbind Saha checkup and meds | C10: 1250 | D10: Expense | E10: 2026-07-02T00:34:36.000 | F10: 2026-07-26T02:48:24.866 | H10: =IF(O10="","",IFERROR(INDEX(Accounts!$B$2:$B$24,MATCH(O10,Accounts!$A$2:$A$24,0)),"Unknown")) | I10: =IF(P10="","",IFERROR(INDEX(Categories!$B$2:$B$25,MATCH(P10,Categories!$A$2:$A$25,0)),"Unknown")) | J10: =IF(Q10="","",IFERROR(INDEX(Accounts!$B$2:$B$24,MATCH(Q10,Accounts!$A$2:$A$24,0)),"Unknown")) | K10: =IF(R10="","",IFERROR(INDEX(Accounts!$B$2:$B$24,MATCH(R10,Accounts!$A$2:$A$24,0)),"Unknown")) | L10: =IF(S10="","",IFERROR(INDEX(People!$B$2:$B$7,MATCH(S10,People!$A$2:$A$7,0)),"Unknown")) | M10: =IF(T10="","",IFERROR(INDEX(Recurrings!$B$2:$B$3,MATCH(T10,Recurrings!$A$2:$A$3,0)),"Unknown")) | N10: =IF(U10="","",IFERROR(INDEX(Users!$B$2:$B$2,MATCH(U10,Users!$A$2:$A$2,0)),"Unknown")) | O10: 8cedd8c1-7bcb-4b94-be6b-e72b888f1084 | P10: 892419eb-083b-410f-b146-1f3c70914aa1 | S10: 7214a9a0-5619-49f8-8521-181d4faf1190 | U10: 814248de-0f8d-4712-bd00-91d12164a414
A11: 10 | B11: Expense | C11: 80 | D11: Expense | E11: 2026-07-03T00:35:00.000 | F11: 2026-07-26T02:48:30.944 | H11: =IF(O11="","",IFERROR(INDEX(Accounts!$B$2:$B$24,MATCH(O11,Accounts!$A$2:$A$24,0)),"Unknown")) | I11: =IF(P11="","",IFERROR(INDEX(Categories!$B$2:$B$25,MATCH(P11,Categories!$A$2:$A$25,0)),"Unknown")) | J11: =IF(Q11="","",IFERROR(INDEX(Accounts!$B$2:$B$24,MATCH(Q11,Accounts!$A$2:$A$24,0)),"Unknown")) | K11: =IF(R11="","",IFERROR(INDEX(Accounts!$B$2:$B$24,MATCH(R11,Accounts!$A$2:$A$24,0)),"Unknown")) | L11: =IF(S11="","",IFERROR(INDEX(People!$B$2:$B$7,MATCH(S11,People!$A$2:$A$7,0)),"Unknown")) | M11: =IF(T11="","",IFERROR(INDEX(Recurrings!$B$2:$B$3,MATCH(T11,Recurrings!$A$2:$A$3,0)),"Unknown")) | N11: =IF(U11="","",IFERROR(INDEX(Users!$B$2:$B$2,MATCH(U11,Users!$A$2:$A$2,0)),"Unknown")) | O11: 8cedd8c1-7bcb-4b94-be6b-e72b888f1084 | P11: 066d9d96-53ec-4eb7-a045-fc8dfb1d33cb | S11: 7214a9a0-5619-49f8-8521-181d4faf1190 | U11: 814248de-0f8d-4712-bd00-91d12164a414
A12: 11 | B12: Expense | C12: 70 | D12: Expense | E12: 2026-07-01T00:35:48.000 | F12: 2026-07-26T02:47:02.542 | H12: =IF(O12="","",IFERROR(INDEX(Accounts!$B$2:$B$24,MATCH(O12,Accounts!$A$2:$A$24,0)),"Unknown")) | I12: =IF(P12="","",IFERROR(INDEX(Categories!$B$2:$B$25,MATCH(P12,Categories!$A$2:$A$25,0)),"Unknown")) | J12: =IF(Q12="","",IFERROR(INDEX(Accounts!$B$2:$B$24,MATCH(Q12,Accounts!$A$2:$A$24,0)),"Unknown")) | K12: =IF(R12="","",IFERROR(INDEX(Accounts!$B$2:$B$24,MATCH(R12,Accounts!$A$2:$A$24,0)),"Unknown")) | L12: =IF(S12="","",IFERROR(INDEX(People!$B$2:$B$7,MATCH(S12,People!$A$2:$A$7,0)),"Unknown")) | M12: =IF(T12="","",IFERROR(INDEX(Recurrings!$B$2:$B$3,MATCH(T12,Recurrings!$A$2:$A$3,0)),"Unknown")) | N12: =IF(U12="","",IFERROR(INDEX(Users!$B$2:$B$2,MATCH(U12,Users!$A$2:$A$2,0)),"Unknown")) | O12: 18110823-8fe5-4547-b1d3-8dbd2cc5b2e3 | P12: 892419eb-083b-410f-b146-1f3c70914aa1 | S12: ca7539c0-14da-430a-ae59-44fee8b96222 | U12: 814248de-0f8d-4712-bd00-91d12164a414
A13: 12 | B13: Expense | C13: 64 | D13: Expense | E13: 2026-07-02T00:36:16.000 | F13: 2026-07-26T02:47:09.293 | H13: =IF(O13="","",IFERROR(INDEX(Accounts!$B$2:$B$24,MATCH(O13,Accounts!$A$2:$A$24,0)),"Unknown")) | I13: =IF(P13="","",IFERROR(INDEX(Categories!$B$2:$B$25,MATCH(P13,Categories!$A$2:$A$25,0)),"Unknown")) | J13: =IF(Q13="","",IFERROR(INDEX(Accounts!$B$2:$B$24,MATCH(Q13,Accounts!$A$2:$A$24,0)),"Unknown")) | K13: =IF(R13="","",IFERROR(INDEX(Accounts!$B$2:$B$24,MATCH(R13,Accounts!$A$2:$A$24,0)),"Unknown")) | L13: =IF(S13="","",IFERROR(INDEX(People!$B$2:$B$7,MATCH(S13,People!$A$2:$A$7,0)),"Unknown")) | M13: =IF(T13="","",IFERROR(INDEX(Recurrings!$B$2:$B$3,MATCH(T13,Recurrings!$A$2:$A$3,0)),"Unknown")) | N13: =IF(U13="","",IFERROR(INDEX(Users!$B$2:$B$2,MATCH(U13,Users!$A$2:$A$2,0)),"Unknown")) | O13: 18110823-8fe5-4547-b1d3-8dbd2cc5b2e3 | P13: 892419eb-083b-410f-b146-1f3c70914aa1 | S13: ca7539c0-14da-430a-ae59-44fee8b96222 | U13: 814248de-0f8d-4712-bd00-91d12164a414
A14: 13 | B14: Expense | C14: 286 | D14: Expense | E14: 2026-07-03T00:36:34.000 | F14: 2026-07-26T02:47:18.033 | H14: =IF(O14="","",IFERROR(INDEX(Accounts!$B$2:$B$24,MATCH(O14,Accounts!$A$2:$A$24,0)),"Unknown")) | I14: =IF(P14="","",IFERROR(INDEX(Categories!$B$2:$B$25,MATCH(P14,Categories!$A$2:$A$25,0)),"Unknown")) | J14: =IF(Q14="","",IFERROR(INDEX(Accounts!$B$2:$B$24,MATCH(Q14,Accounts!$A$2:$A$24,0)),"Unknown")) | K14: =IF(R14="","",IFERROR(INDEX(Accounts!$B$2:$B$24,MATCH(R14,Accounts!$A$2:$A$24,0)),"Unknown")) | L14: =IF(S14="","",IFERROR(INDEX(People!$B$2:$B$7,MATCH(S14,People!$A$2:$A$7,0)),"Unknown")) | M14: =IF(T14="","",IFERROR(INDEX(Recurrings!$B$2:$B$3,MATCH(T14,Recurrings!$A$2:$A$3,0)),"Unknown")) | N14: =IF(U14="","",IFERROR(INDEX(Users!$B$2:$B$2,MATCH(U14,Users!$A$2:$A$2,0)),"Unknown")) | O14: 18110823-8fe5-4547-b1d3-8dbd2cc5b2e3 | P14: 892419eb-083b-410f-b146-1f3c70914aa1 | S14: ca7539c0-14da-430a-ae59-44fee8b96222 | U14: 814248de-0f8d-4712-bd00-91d12164a414
A15: 14 | B15: Savings | C15: 267280 | D15: Income | E15: 2026-07-04T00:37:57.260 | F15: 2026-07-04T00:37:57.260 | H15: =IF(O15="","",IFERROR(INDEX(Accounts!$B$2:$B$24,MATCH(O15,Accounts!$A$2:$A$24,0)),"Unknown")) | I15: =IF(P15="","",IFERROR(INDEX(Categories!$B$2:$B$25,MATCH(P15,Categories!$A$2:$A$25,0)),"Unknown")) | J15: =IF(Q15="","",IFERROR(INDEX(Accounts!$B$2:$B$24,MATCH(Q15,Accounts!$A$2:$A$24,0)),"Unknown")) | K15: =IF(R15="","",IFERROR(INDEX(Accounts!$B$2:$B$24,MATCH(R15,Accounts!$A$2:$A$24,0)),"Unknown")) | L15: =IF(S15="","",IFERROR(INDEX(People!$B$2:$B$7,MATCH(S15,People!$A$2:$A$7,0)),"Unknown")) | M15: =IF(T15="","",IFERROR(INDEX(Recurrings!$B$2:$B$3,MATCH(T15,Recurrings!$A$2:$A$3,0)),"Unknown")) | N15: =IF(U15="","",IFERROR(INDEX(Users!$B$2:$B$2,MATCH(U15,Users!$A$2:$A$2,0)),"Unknown")) | O15: a5b44f57-40f5-4b0e-96db-1179f20d75d0 | P15: 1c612037-9067-4e69-aebc-14619b77b363 | U15: 814248de-0f8d-4712-bd00-91d12164a414
A16: 15 | B16: Uttam jewellers | C16: 100000 | D16: Expense | E16: 2026-07-03T20:15:58.000 | F16: 2026-07-26T02:49:05.806 | G16: 24 gm gold adv | H16: =IF(O16="","",IFERROR(INDEX(Accounts!$B$2:$B$24,MATCH(O16,Accounts!$A$2:$A$24,0)),"Unknown")) | I16: =IF(P16="","",IFERROR(INDEX(Categories!$B$2:$B$25,MATCH(P16,Categories!$A$2:$A$25,0)),"Unknown")) | J16: =IF(Q16="","",IFERROR(INDEX(Accounts!$B$2:$B$24,MATCH(Q16,Accounts!$A$2:$A$24,0)),"Unknown")) | K16: =IF(R16="","",IFERROR(INDEX(Accounts!$B$2:$B$24,MATCH(R16,Accounts!$A$2:$A$24,0)),"Unknown")) | L16: =IF(S16="","",IFERROR(INDEX(People!$B$2:$B$7,MATCH(S16,People!$A$2:$A$7,0)),"Unknown")) | M16: =IF(T16="","",IFERROR(INDEX(Recurrings!$B$2:$B$3,MATCH(T16,Recurrings!$A$2:$A$3,0)),"Unknown")) | N16: =IF(U16="","",IFERROR(INDEX(Users!$B$2:$B$2,MATCH(U16,Users!$A$2:$A$2,0)),"Unknown")) | O16: 6b8aeda1-8500-4f9c-996c-55ad6f6d1bf3 | P16: d4addfc4-44b5-4628-8237-9afb254f475b | S16: 7214a9a0-5619-49f8-8521-181d4faf1190 | U16: 814248de-0f8d-4712-bd00-91d12164a414
A17: 16 | B17: Deposit | C17: 50000 | D17: Transfer | E17: 2026-07-04T20:17:53.000 | F17: 2026-07-04T20:18:18.933 | H17: =IF(O17="","",IFERROR(INDEX(Accounts!$B$2:$B$24,MATCH(O17,Accounts!$A$2:$A$24,0)),"Unknown")) | I17: =IF(P17="","",IFERROR(INDEX(Categories!$B$2:$B$25,MATCH(P17,Categories!$A$2:$A$25,0)),"Unknown")) | J17: =IF(Q17="","",IFERROR(INDEX(Accounts!$B$2:$B$24,MATCH(Q17,Accounts!$A$2:$A$24,0)),"Unknown")) | K17: =IF(R17="","",IFERROR(INDEX(Accounts!$B$2:$B$24,MATCH(R17,Accounts!$A$2:$A$24,0)),"Unknown")) | L17: =IF(S17="","",IFERROR(INDEX(People!$B$2:$B$7,MATCH(S17,People!$A$2:$A$7,0)),"Unknown")) | M17: =IF(T17="","",IFERROR(INDEX(Recurrings!$B$2:$B$3,MATCH(T17,Recurrings!$A$2:$A$3,0)),"Unknown")) | N17: =IF(U17="","",IFERROR(INDEX(Users!$B$2:$B$2,MATCH(U17,Users!$A$2:$A$2,0)),"Unknown")) | Q17: a5b44f57-40f5-4b0e-96db-1179f20d75d0 | R17: 2b9af0c9-8855-4666-9be1-4c781d9f1ec3 | U17: 814248de-0f8d-4712-bd00-91d12164a414
A18: 17 | B18: Deposit | C18: 11000 | D18: Transfer | E18: 2026-07-04T20:21:25.767 | F18: 2026-07-04T20:21:25.767 | H18: =IF(O18="","",IFERROR(INDEX(Accounts!$B$2:$B$24,MATCH(O18,Accounts!$A$2:$A$24,0)),"Unknown")) | I18: =IF(P18="","",IFERROR(INDEX(Categories!$B$2:$B$25,MATCH(P18,Categories!$A$2:$A$25,0)),"Unknown")) | J18: =IF(Q18="","",IFERROR(INDEX(Accounts!$B$2:$B$24,MATCH(Q18,Accounts!$A$2:$A$24,0)),"Unknown")) | K18: =IF(R18="","",IFERROR(INDEX(Accounts!$B$2:$B$24,MATCH(R18,Accounts!$A$2:$A$24,0)),"Unknown")) | L18: =IF(S18="","",IFERROR(INDEX(People!$B$2:$B$7,MATCH(S18,People!$A$2:$A$7,0)),"Unknown")) | M18: =IF(T18="","",IFERROR(INDEX(Recurrings!$B$2:$B$3,MATCH(T18,Recurrings!$A$2:$A$3,0)),"Unknown")) | N18: =IF(U18="","",IFERROR(INDEX(Users!$B$2:$B$2,MATCH(U18,Users!$A$2:$A$2,0)),"Unknown")) | Q18: 4b9fa03c-eddf-42ff-8d5f-eaa9e3086ce0 | R18: 2b9af0c9-8855-4666-9be1-4c781d9f1ec3 | U18: 814248de-0f8d-4712-bd00-91d12164a414
A19: 18 | B19: Spotify premium | C19: 59 | D19: Expense | E19: 2026-07-01T20:43:00.811 | F19: 2026-07-04T20:44:03.418 | H19: =IF(O19="","",IFERROR(INDEX(Accounts!$B$2:$B$24,MATCH(O19,Accounts!$A$2:$A$24,0)),"Unknown")) | I19: =IF(P19="","",IFERROR(INDEX(Categories!$B$2:$B$25,MATCH(P19,Categories!$A$2:$A$25,0)),"Unknown")) | J19: =IF(Q19="","",IFERROR(INDEX(Accounts!$B$2:$B$24,MATCH(Q19,Accounts!$A$2:$A$24,0)),"Unknown")) | K19: =IF(R19="","",IFERROR(INDEX(Accounts!$B$2:$B$24,MATCH(R19,Accounts!$A$2:$A$24,0)),"Unknown")) | L19: =IF(S19="","",IFERROR(INDEX(People!$B$2:$B$7,MATCH(S19,People!$A$2:$A$7,0)),"Unknown")) | M19: =IF(T19="","",IFERROR(INDEX(Recurrings!$B$2:$B$3,MATCH(T19,Recurrings!$A$2:$A$3,0)),"Unknown")) | N19: =IF(U19="","",IFERROR(INDEX(Users!$B$2:$B$2,MATCH(U19,Users!$A$2:$A$2,0)),"Unknown")) | O19: a5b44f57-40f5-4b0e-96db-1179f20d75d0 | P19: 892419eb-083b-410f-b146-1f3c70914aa1 | T19: c893b300-6371-4ec2-b676-904a53f5443f | U19: 814248de-0f8d-4712-bd00-91d12164a414
A20: 19 | B20: Office Transport Leverage | C20: 200 | D20: Income | E20: 2026-07-02T20:44:45.223 | F20: 2026-07-04T20:48:36.862 | H20: =IF(O20="","",IFERROR(INDEX(Accounts!$B$2:$B$24,MATCH(O20,Accounts!$A$2:$A$24,0)),"Unknown")) | I20: =IF(P20="","",IFERROR(INDEX(Categories!$B$2:$B$25,MATCH(P20,Categories!$A$2:$A$25,0)),"Unknown")) | J20: =IF(Q20="","",IFERROR(INDEX(Accounts!$B$2:$B$24,MATCH(Q20,Accounts!$A$2:$A$24,0)),"Unknown")) | K20: =IF(R20="","",IFERROR(INDEX(Accounts!$B$2:$B$24,MATCH(R20,Accounts!$A$2:$A$24,0)),"Unknown")) | L20: =IF(S20="","",IFERROR(INDEX(People!$B$2:$B$7,MATCH(S20,People!$A$2:$A$7,0)),"Unknown")) | M20: =IF(T20="","",IFERROR(INDEX(Recurrings!$B$2:$B$3,MATCH(T20,Recurrings!$A$2:$A$3,0)),"Unknown")) | N20: =IF(U20="","",IFERROR(INDEX(Users!$B$2:$B$2,MATCH(U20,Users!$A$2:$A$2,0)),"Unknown")) | O20: f89518bd-b7d1-4658-9692-994af79cfcb8 | P20: f894a6a7-dfc4-4c79-bf71-b2526dc474ac | T20: 5f717740-b341-4fec-9dee-eb1c70d3c260 | U20: 814248de-0f8d-4712-bd00-91d12164a414
A21: 22 | B21: Daily office transport perk | C21: 200 | D21: Income | E21: 2026-06-29T20:49:42.000 | F21: 2026-07-04T20:50:19.391 | H21: =IF(O21="","",IFERROR(INDEX(Accounts!$B$2:$B$24,MATCH(O21,Accounts!$A$2:$A$24,0)),"Unknown")) | I21: =IF(P21="","",IFERROR(INDEX(Categories!$B$2:$B$25,MATCH(P21,Categories!$A$2:$A$25,0)),"Unknown")) | J21: =IF(Q21="","",IFERROR(INDEX(Accounts!$B$2:$B$24,MATCH(Q21,Accounts!$A$2:$A$24,0)),"Unknown")) | K21: =IF(R21="","",IFERROR(INDEX(Accounts!$B$2:$B$24,MATCH(R21,Accounts!$A$2:$A$24,0)),"Unknown")) | L21: =IF(S21="","",IFERROR(INDEX(People!$B$2:$B$7,MATCH(S21,People!$A$2:$A$7,0)),"Unknown")) | M21: =IF(T21="","",IFERROR(INDEX(Recurrings!$B$2:$B$3,MATCH(T21,Recurrings!$A$2:$A$3,0)),"Unknown")) | N21: =IF(U21="","",IFERROR(INDEX(Users!$B$2:$B$2,MATCH(U21,Users!$A$2:$A$2,0)),"Unknown")) | O21: f89518bd-b7d1-4658-9692-994af79cfcb8 | P21: f894a6a7-dfc4-4c79-bf71-b2526dc474ac | U21: 814248de-0f8d-4712-bd00-91d12164a414
A22: 23 | B22: Daily office transport perk | C22: 200 | D22: Income | E22: 2026-06-30T20:50:42.000 | F22: 2026-07-04T20:51:07.056 | H22: =IF(O22="","",IFERROR(INDEX(Accounts!$B$2:$B$24,MATCH(O22,Accounts!$A$2:$A$24,0)),"Unknown")) | I22: =IF(P22="","",IFERROR(INDEX(Categories!$B$2:$B$25,MATCH(P22,Categories!$A$2:$A$25,0)),"Unknown")) | J22: =IF(Q22="","",IFERROR(INDEX(Accounts!$B$2:$B$24,MATCH(Q22,Accounts!$A$2:$A$24,0)),"Unknown")) | K22: =IF(R22="","",IFERROR(INDEX(Accounts!$B$2:$B$24,MATCH(R22,Accounts!$A$2:$A$24,0)),"Unknown")) | L22: =IF(S22="","",IFERROR(INDEX(People!$B$2:$B$7,MATCH(S22,People!$A$2:$A$7,0)),"Unknown")) | M22: =IF(T22="","",IFERROR(INDEX(Recurrings!$B$2:$B$3,MATCH(T22,Recurrings!$A$2:$A$3,0)),"Unknown")) | N22: =IF(U22="","",IFERROR(INDEX(Users!$B$2:$B$2,MATCH(U22,Users!$A$2:$A$2,0)),"Unknown")) | O22: f89518bd-b7d1-4658-9692-994af79cfcb8 | P22: f894a6a7-dfc4-4c79-bf71-b2526dc474ac | U22: 814248de-0f8d-4712-bd00-91d12164a414
A23: 24 | B23: Snacks | C23: 130 | D23: Income | E23: 2026-07-02T20:53:32.000 | F23: 2026-07-17T14:47:22.810 | G23: Paid on 6th july | H23: =IF(O23="","",IFERROR(INDEX(Accounts!$B$2:$B$24,MATCH(O23,Accounts!$A$2:$A$24,0)),"Unknown")) | I23: =IF(P23="","",IFERROR(INDEX(Categories!$B$2:$B$25,MATCH(P23,Categories!$A$2:$A$25,0)),"Unknown")) | J23: =IF(Q23="","",IFERROR(INDEX(Accounts!$B$2:$B$24,MATCH(Q23,Accounts!$A$2:$A$24,0)),"Unknown")) | K23: =IF(R23="","",IFERROR(INDEX(Accounts!$B$2:$B$24,MATCH(R23,Accounts!$A$2:$A$24,0)),"Unknown")) | L23: =IF(S23="","",IFERROR(INDEX(People!$B$2:$B$7,MATCH(S23,People!$A$2:$A$7,0)),"Unknown")) | M23: =IF(T23="","",IFERROR(INDEX(Recurrings!$B$2:$B$3,MATCH(T23,Recurrings!$A$2:$A$3,0)),"Unknown")) | N23: =IF(U23="","",IFERROR(INDEX(Users!$B$2:$B$2,MATCH(U23,Users!$A$2:$A$2,0)),"Unknown")) | O23: 7aeb233a-f5a8-4242-9a4a-0b401a7cf99b | P23: e437a0b5-5f69-4f5b-b879-b8de520215cc | U23: 814248de-0f8d-4712-bd00-91d12164a414
A24: 25 | B24: Expense | C24: 122 | D24: Expense | E24: 2026-07-04T23:05:11.900 | F24: 2026-07-26T02:47:24.733 | H24: =IF(O24="","",IFERROR(INDEX(Accounts!$B$2:$B$24,MATCH(O24,Accounts!$A$2:$A$24,0)),"Unknown")) | I24: =IF(P24="","",IFERROR(INDEX(Categories!$B$2:$B$25,MATCH(P24,Categories!$A$2:$A$25,0)),"Unknown")) | J24: =IF(Q24="","",IFERROR(INDEX(Accounts!$B$2:$B$24,MATCH(Q24,Accounts!$A$2:$A$24,0)),"Unknown")) | K24: =IF(R24="","",IFERROR(INDEX(Accounts!$B$2:$B$24,MATCH(R24,Accounts!$A$2:$A$24,0)),"Unknown")) | L24: =IF(S24="","",IFERROR(INDEX(People!$B$2:$B$7,MATCH(S24,People!$A$2:$A$7,0)),"Unknown")) | M24: =IF(T24="","",IFERROR(INDEX(Recurrings!$B$2:$B$3,MATCH(T24,Recurrings!$A$2:$A$3,0)),"Unknown")) | N24: =IF(U24="","",IFERROR(INDEX(Users!$B$2:$B$2,MATCH(U24,Users!$A$2:$A$2,0)),"Unknown")) | O24: 18110823-8fe5-4547-b1d3-8dbd2cc5b2e3 | P24: 892419eb-083b-410f-b146-1f3c70914aa1 | S24: ca7539c0-14da-430a-ae59-44fee8b96222 | U24: 814248de-0f8d-4712-bd00-91d12164a414
A25: 26 | B25: Cashback | C25: 500 | D25: Income | E25: 2026-07-01T15:39:25.000 | F25: 2026-07-05T15:39:47.888 | H25: =IF(O25="","",IFERROR(INDEX(Accounts!$B$2:$B$24,MATCH(O25,Accounts!$A$2:$A$24,0)),"Unknown")) | I25: =IF(P25="","",IFERROR(INDEX(Categories!$B$2:$B$25,MATCH(P25,Categories!$A$2:$A$25,0)),"Unknown")) | J25: =IF(Q25="","",IFERROR(INDEX(Accounts!$B$2:$B$24,MATCH(Q25,Accounts!$A$2:$A$24,0)),"Unknown")) | K25: =IF(R25="","",IFERROR(INDEX(Accounts!$B$2:$B$24,MATCH(R25,Accounts!$A$2:$A$24,0)),"Unknown")) | L25: =IF(S25="","",IFERROR(INDEX(People!$B$2:$B$7,MATCH(S25,People!$A$2:$A$7,0)),"Unknown")) | M25: =IF(T25="","",IFERROR(INDEX(Recurrings!$B$2:$B$3,MATCH(T25,Recurrings!$A$2:$A$3,0)),"Unknown")) | N25: =IF(U25="","",IFERROR(INDEX(Users!$B$2:$B$2,MATCH(U25,Users!$A$2:$A$2,0)),"Unknown")) | O25: 855f5acb-cf90-4eed-bef4-7733fec688b6 | P25: 1c612037-9067-4e69-aebc-14619b77b363 | U25: 814248de-0f8d-4712-bd00-91d12164a414
A26: 27 | B26: Swiggy tandoori wings | C26: 140 | D26: Expense | E26: 2026-07-04T15:39:53.000 | F26: 2026-07-05T15:40:18.551 | H26: =IF(O26="","",IFERROR(INDEX(Accounts!$B$2:$B$24,MATCH(O26,Accounts!$A$2:$A$24,0)),"Unknown")) | I26: =IF(P26="","",IFERROR(INDEX(Categories!$B$2:$B$25,MATCH(P26,Categories!$A$2:$A$25,0)),"Unknown")) | J26: =IF(Q26="","",IFERROR(INDEX(Accounts!$B$2:$B$24,MATCH(Q26,Accounts!$A$2:$A$24,0)),"Unknown")) | K26: =IF(R26="","",IFERROR(INDEX(Accounts!$B$2:$B$24,MATCH(R26,Accounts!$A$2:$A$24,0)),"Unknown")) | L26: =IF(S26="","",IFERROR(INDEX(People!$B$2:$B$7,MATCH(S26,People!$A$2:$A$7,0)),"Unknown")) | M26: =IF(T26="","",IFERROR(INDEX(Recurrings!$B$2:$B$3,MATCH(T26,Recurrings!$A$2:$A$3,0)),"Unknown")) | N26: =IF(U26="","",IFERROR(INDEX(Users!$B$2:$B$2,MATCH(U26,Users!$A$2:$A$2,0)),"Unknown")) | O26: 855f5acb-cf90-4eed-bef4-7733fec688b6 | P26: 9ea0a2b1-4b22-40a4-81ab-843452f9c274 | U26: 814248de-0f8d-4712-bd00-91d12164a414
A27: 28 | B27: Reward redemption charges | C27: 116.82 | D27: Expense | E27: 2026-07-03T15:40:39.000 | F27: 2026-07-06T17:25:42.376 | H27: =IF(O27="","",IFERROR(INDEX(Accounts!$B$2:$B$24,MATCH(O27,Accounts!$A$2:$A$24,0)),"Unknown")) | I27: =IF(P27="","",IFERROR(INDEX(Categories!$B$2:$B$25,MATCH(P27,Categories!$A$2:$A$25,0)),"Unknown")) | J27: =IF(Q27="","",IFERROR(INDEX(Accounts!$B$2:$B$24,MATCH(Q27,Accounts!$A$2:$A$24,0)),"Unknown")) | K27: =IF(R27="","",IFERROR(INDEX(Accounts!$B$2:$B$24,MATCH(R27,Accounts!$A$2:$A$24,0)),"Unknown")) | L27: =IF(S27="","",IFERROR(INDEX(People!$B$2:$B$7,MATCH(S27,People!$A$2:$A$7,0)),"Unknown")) | M27: =IF(T27="","",IFERROR(INDEX(Recurrings!$B$2:$B$3,MATCH(T27,Recurrings!$A$2:$A$3,0)),"Unknown")) | N27: =IF(U27="","",IFERROR(INDEX(Users!$B$2:$B$2,MATCH(U27,Users!$A$2:$A$2,0)),"Unknown")) | O27: b97245b7-cfde-4557-9035-8297edba21af | P27: 892419eb-083b-410f-b146-1f3c70914aa1 | U27: 814248de-0f8d-4712-bd00-91d12164a414
A28: 29 | B28: Cc credit | C28: 34479 | D28: Expense | E28: 2026-07-05T15:56:16.942 | F28: 2026-07-05T15:56:16.942 | H28: =IF(O28="","",IFERROR(INDEX(Accounts!$B$2:$B$24,MATCH(O28,Accounts!$A$2:$A$24,0)),"Unknown")) | I28: =IF(P28="","",IFERROR(INDEX(Categories!$B$2:$B$25,MATCH(P28,Categories!$A$2:$A$25,0)),"Unknown")) | J28: =IF(Q28="","",IFERROR(INDEX(Accounts!$B$2:$B$24,MATCH(Q28,Accounts!$A$2:$A$24,0)),"Unknown")) | K28: =IF(R28="","",IFERROR(INDEX(Accounts!$B$2:$B$24,MATCH(R28,Accounts!$A$2:$A$24,0)),"Unknown")) | L28: =IF(S28="","",IFERROR(INDEX(People!$B$2:$B$7,MATCH(S28,People!$A$2:$A$7,0)),"Unknown")) | M28: =IF(T28="","",IFERROR(INDEX(Recurrings!$B$2:$B$3,MATCH(T28,Recurrings!$A$2:$A$3,0)),"Unknown")) | N28: =IF(U28="","",IFERROR(INDEX(Users!$B$2:$B$2,MATCH(U28,Users!$A$2:$A$2,0)),"Unknown")) | O28: aa69aba3-4e60-426d-adfa-15f984249883 | P28: 892419eb-083b-410f-b146-1f3c70914aa1 | U28: 814248de-0f8d-4712-bd00-91d12164a414
A29: 30 | B29: Milk eggs dahi | C29: 106 | D29: Expense | E29: 2026-07-05T20:12:18.684 | F29: 2026-07-05T20:12:18.684 | H29: =IF(O29="","",IFERROR(INDEX(Accounts!$B$2:$B$24,MATCH(O29,Accounts!$A$2:$A$24,0)),"Unknown")) | I29: =IF(P29="","",IFERROR(INDEX(Categories!$B$2:$B$25,MATCH(P29,Categories!$A$2:$A$25,0)),"Unknown")) | J29: =IF(Q29="","",IFERROR(INDEX(Accounts!$B$2:$B$24,MATCH(Q29,Accounts!$A$2:$A$24,0)),"Unknown")) | K29: =IF(R29="","",IFERROR(INDEX(Accounts!$B$2:$B$24,MATCH(R29,Accounts!$A$2:$A$24,0)),"Unknown")) | L29: =IF(S29="","",IFERROR(INDEX(People!$B$2:$B$7,MATCH(S29,People!$A$2:$A$7,0)),"Unknown")) | M29: =IF(T29="","",IFERROR(INDEX(Recurrings!$B$2:$B$3,MATCH(T29,Recurrings!$A$2:$A$3,0)),"Unknown")) | N29: =IF(U29="","",IFERROR(INDEX(Users!$B$2:$B$2,MATCH(U29,Users!$A$2:$A$2,0)),"Unknown")) | O29: aa69aba3-4e60-426d-adfa-15f984249883 | P29: 066d9d96-53ec-4eb7-a045-fc8dfb1d33cb | U29: 814248de-0f8d-4712-bd00-91d12164a414
A30: 31 | B30: Fruits | C30: 57 | D30: Expense | E30: 2026-07-05T20:12:32.035 | F30: 2026-07-05T20:12:32.035 | H30: =IF(O30="","",IFERROR(INDEX(Accounts!$B$2:$B$24,MATCH(O30,Accounts!$A$2:$A$24,0)),"Unknown")) | I30: =IF(P30="","",IFERROR(INDEX(Categories!$B$2:$B$25,MATCH(P30,Categories!$A$2:$A$25,0)),"Unknown")) | J30: =IF(Q30="","",IFERROR(INDEX(Accounts!$B$2:$B$24,MATCH(Q30,Accounts!$A$2:$A$24,0)),"Unknown")) | K30: =IF(R30="","",IFERROR(INDEX(Accounts!$B$2:$B$24,MATCH(R30,Accounts!$A$2:$A$24,0)),"Unknown")) | L30: =IF(S30="","",IFERROR(INDEX(People!$B$2:$B$7,MATCH(S30,People!$A$2:$A$7,0)),"Unknown")) | M30: =IF(T30="","",IFERROR(INDEX(Recurrings!$B$2:$B$3,MATCH(T30,Recurrings!$A$2:$A$3,0)),"Unknown")) | N30: =IF(U30="","",IFERROR(INDEX(Users!$B$2:$B$2,MATCH(U30,Users!$A$2:$A$2,0)),"Unknown")) | O30: 4b9fa03c-eddf-42ff-8d5f-eaa9e3086ce0 | P30: 9ea0a2b1-4b22-40a4-81ab-843452f9c274 | U30: 814248de-0f8d-4712-bd00-91d12164a414
A31: 32 | B31: Expense | C31: 560 | D31: Expense | E31: 2026-07-05T20:13:03.527 | F31: 2026-07-26T02:48:35.731 | H31: =IF(O31="","",IFERROR(INDEX(Accounts!$B$2:$B$24,MATCH(O31,Accounts!$A$2:$A$24,0)),"Unknown")) | I31: =IF(P31="","",IFERROR(INDEX(Categories!$B$2:$B$25,MATCH(P31,Categories!$A$2:$A$25,0)),"Unknown")) | J31: =IF(Q31="","",IFERROR(INDEX(Accounts!$B$2:$B$24,MATCH(Q31,Accounts!$A$2:$A$24,0)),"Unknown")) | K31: =IF(R31="","",IFERROR(INDEX(Accounts!$B$2:$B$24,MATCH(R31,Accounts!$A$2:$A$24,0)),"Unknown")) | L31: =IF(S31="","",IFERROR(INDEX(People!$B$2:$B$7,MATCH(S31,People!$A$2:$A$7,0)),"Unknown")) | M31: =IF(T31="","",IFERROR(INDEX(Recurrings!$B$2:$B$3,MATCH(T31,Recurrings!$A$2:$A$3,0)),"Unknown")) | N31: =IF(U31="","",IFERROR(INDEX(Users!$B$2:$B$2,MATCH(U31,Users!$A$2:$A$2,0)),"Unknown")) | O31: 8cedd8c1-7bcb-4b94-be6b-e72b888f1084 | P31: 066d9d96-53ec-4eb7-a045-fc8dfb1d33cb | S31: 7214a9a0-5619-49f8-8521-181d4faf1190 | U31: 814248de-0f8d-4712-bd00-91d12164a414
A32: 33 | B32: Expense | C32: 236 | D32: Expense | E32: 2026-07-05T23:44:26.945 | F32: 2026-07-26T02:47:31.060 | H32: =IF(O32="","",IFERROR(INDEX(Accounts!$B$2:$B$24,MATCH(O32,Accounts!$A$2:$A$24,0)),"Unknown")) | I32: =IF(P32="","",IFERROR(INDEX(Categories!$B$2:$B$25,MATCH(P32,Categories!$A$2:$A$25,0)),"Unknown")) | J32: =IF(Q32="","",IFERROR(INDEX(Accounts!$B$2:$B$24,MATCH(Q32,Accounts!$A$2:$A$24,0)),"Unknown")) | K32: =IF(R32="","",IFERROR(INDEX(Accounts!$B$2:$B$24,MATCH(R32,Accounts!$A$2:$A$24,0)),"Unknown")) | L32: =IF(S32="","",IFERROR(INDEX(People!$B$2:$B$7,MATCH(S32,People!$A$2:$A$7,0)),"Unknown")) | M32: =IF(T32="","",IFERROR(INDEX(Recurrings!$B$2:$B$3,MATCH(T32,Recurrings!$A$2:$A$3,0)),"Unknown")) | N32: =IF(U32="","",IFERROR(INDEX(Users!$B$2:$B$2,MATCH(U32,Users!$A$2:$A$2,0)),"Unknown")) | O32: 18110823-8fe5-4547-b1d3-8dbd2cc5b2e3 | P32: 892419eb-083b-410f-b146-1f3c70914aa1 | S32: ca7539c0-14da-430a-ae59-44fee8b96222 | U32: 814248de-0f8d-4712-bd00-91d12164a414
A33: 34 | B33: Shubham ko diya | C33: 100 | D33: Expense | E33: 2026-07-05T00:28:40.000 | F33: 2026-07-06T00:29:10.441 | H33: =IF(O33="","",IFERROR(INDEX(Accounts!$B$2:$B$24,MATCH(O33,Accounts!$A$2:$A$24,0)),"Unknown")) | I33: =IF(P33="","",IFERROR(INDEX(Categories!$B$2:$B$25,MATCH(P33,Categories!$A$2:$A$25,0)),"Unknown")) | J33: =IF(Q33="","",IFERROR(INDEX(Accounts!$B$2:$B$24,MATCH(Q33,Accounts!$A$2:$A$24,0)),"Unknown")) | K33: =IF(R33="","",IFERROR(INDEX(Accounts!$B$2:$B$24,MATCH(R33,Accounts!$A$2:$A$24,0)),"Unknown")) | L33: =IF(S33="","",IFERROR(INDEX(People!$B$2:$B$7,MATCH(S33,People!$A$2:$A$7,0)),"Unknown")) | M33: =IF(T33="","",IFERROR(INDEX(Recurrings!$B$2:$B$3,MATCH(T33,Recurrings!$A$2:$A$3,0)),"Unknown")) | N33: =IF(U33="","",IFERROR(INDEX(Users!$B$2:$B$2,MATCH(U33,Users!$A$2:$A$2,0)),"Unknown")) | O33: a5b44f57-40f5-4b0e-96db-1179f20d75d0 | P33: b5eb22d9-3779-43fc-99af-eded3ff9bcd8 | U33: 814248de-0f8d-4712-bd00-91d12164a414
A34: 35 | B34: Lunch | C34: 65 | D34: Expense | E34: 2026-07-06T13:39:17.797 | F34: 2026-07-06T13:39:17.797 | H34: =IF(O34="","",IFERROR(INDEX(Accounts!$B$2:$B$24,MATCH(O34,Accounts!$A$2:$A$24,0)),"Unknown")) | I34: =IF(P34="","",IFERROR(INDEX(Categories!$B$2:$B$25,MATCH(P34,Categories!$A$2:$A$25,0)),"Unknown")) | J34: =IF(Q34="","",IFERROR(INDEX(Accounts!$B$2:$B$24,MATCH(Q34,Accounts!$A$2:$A$24,0)),"Unknown")) | K34: =IF(R34="","",IFERROR(INDEX(Accounts!$B$2:$B$24,MATCH(R34,Accounts!$A$2:$A$24,0)),"Unknown")) | L34: =IF(S34="","",IFERROR(INDEX(People!$B$2:$B$7,MATCH(S34,People!$A$2:$A$7,0)),"Unknown")) | M34: =IF(T34="","",IFERROR(INDEX(Recurrings!$B$2:$B$3,MATCH(T34,Recurrings!$A$2:$A$3,0)),"Unknown")) | N34: =IF(U34="","",IFERROR(INDEX(Users!$B$2:$B$2,MATCH(U34,Users!$A$2:$A$2,0)),"Unknown")) | O34: a5b44f57-40f5-4b0e-96db-1179f20d75d0 | P34: 9ea0a2b1-4b22-40a4-81ab-843452f9c274 | U34: 814248de-0f8d-4712-bd00-91d12164a414
A35: 36 | B35: Amazon shopping | C35: 3470 | D35: Expense | E35: 2026-07-06T17:25:08.579 | F35: 2026-07-06T17:25:08.579 | G35: Dipen and mom | H35: =IF(O35="","",IFERROR(INDEX(Accounts!$B$2:$B$24,MATCH(O35,Accounts!$A$2:$A$24,0)),"Unknown")) | I35: =IF(P35="","",IFERROR(INDEX(Categories!$B$2:$B$25,MATCH(P35,Categories!$A$2:$A$25,0)),"Unknown")) | J35: =IF(Q35="","",IFERROR(INDEX(Accounts!$B$2:$B$24,MATCH(Q35,Accounts!$A$2:$A$24,0)),"Unknown")) | K35: =IF(R35="","",IFERROR(INDEX(Accounts!$B$2:$B$24,MATCH(R35,Accounts!$A$2:$A$24,0)),"Unknown")) | L35: =IF(S35="","",IFERROR(INDEX(People!$B$2:$B$7,MATCH(S35,People!$A$2:$A$7,0)),"Unknown")) | M35: =IF(T35="","",IFERROR(INDEX(Recurrings!$B$2:$B$3,MATCH(T35,Recurrings!$A$2:$A$3,0)),"Unknown")) | N35: =IF(U35="","",IFERROR(INDEX(Users!$B$2:$B$2,MATCH(U35,Users!$A$2:$A$2,0)),"Unknown")) | O35: b97245b7-cfde-4557-9035-8297edba21af | P35: d1a09f78-95d2-4fb3-9dd1-1ae8a33fa3d8 | U35: 814248de-0f8d-4712-bd00-91d12164a414
A36: 37 | B36: Office Transport Leverage | C36: 200 | D36: Income | E36: 2026-07-06T20:44:45.223 | F36: 2026-07-06T18:41:08.053 | H36: =IF(O36="","",IFERROR(INDEX(Accounts!$B$2:$B$24,MATCH(O36,Accounts!$A$2:$A$24,0)),"Unknown")) | I36: =IF(P36="","",IFERROR(INDEX(Categories!$B$2:$B$25,MATCH(P36,Categories!$A$2:$A$25,0)),"Unknown")) | J36: =IF(Q36="","",IFERROR(INDEX(Accounts!$B$2:$B$24,MATCH(Q36,Accounts!$A$2:$A$24,0)),"Unknown")) | K36: =IF(R36="","",IFERROR(INDEX(Accounts!$B$2:$B$24,MATCH(R36,Accounts!$A$2:$A$24,0)),"Unknown")) | L36: =IF(S36="","",IFERROR(INDEX(People!$B$2:$B$7,MATCH(S36,People!$A$2:$A$7,0)),"Unknown")) | M36: =IF(T36="","",IFERROR(INDEX(Recurrings!$B$2:$B$3,MATCH(T36,Recurrings!$A$2:$A$3,0)),"Unknown")) | N36: =IF(U36="","",IFERROR(INDEX(Users!$B$2:$B$2,MATCH(U36,Users!$A$2:$A$2,0)),"Unknown")) | O36: f89518bd-b7d1-4658-9692-994af79cfcb8 | P36: f894a6a7-dfc4-4c79-bf71-b2526dc474ac | T36: 5f717740-b341-4fec-9dee-eb1c70d3c260 | U36: 814248de-0f8d-4712-bd00-91d12164a414
A37: 38 | B37: Office fare | C37: 27 | D37: Expense | E37: 2026-07-06T19:04:56.938 | F37: 2026-07-06T19:04:56.938 | H37: =IF(O37="","",IFERROR(INDEX(Accounts!$B$2:$B$24,MATCH(O37,Accounts!$A$2:$A$24,0)),"Unknown")) | I37: =IF(P37="","",IFERROR(INDEX(Categories!$B$2:$B$25,MATCH(P37,Categories!$A$2:$A$25,0)),"Unknown")) | J37: =IF(Q37="","",IFERROR(INDEX(Accounts!$B$2:$B$24,MATCH(Q37,Accounts!$A$2:$A$24,0)),"Unknown")) | K37: =IF(R37="","",IFERROR(INDEX(Accounts!$B$2:$B$24,MATCH(R37,Accounts!$A$2:$A$24,0)),"Unknown")) | L37: =IF(S37="","",IFERROR(INDEX(People!$B$2:$B$7,MATCH(S37,People!$A$2:$A$7,0)),"Unknown")) | M37: =IF(T37="","",IFERROR(INDEX(Recurrings!$B$2:$B$3,MATCH(T37,Recurrings!$A$2:$A$3,0)),"Unknown")) | N37: =IF(U37="","",IFERROR(INDEX(Users!$B$2:$B$2,MATCH(U37,Users!$A$2:$A$2,0)),"Unknown")) | O37: 7f7a9ca8-7be5-4ea0-811a-63e598d2c6d3 | P37: 59cb1d7a-195c-4fef-b7e6-682eb97de8a7 | U37: 814248de-0f8d-4712-bd00-91d12164a414
A38: 39 | B38: Pixel 10 pro case moonstone | C38: 2244 | D38: Expense | E38: 2026-07-06T21:11:29.142 | F38: 2026-07-06T21:11:29.142 | H38: =IF(O38="","",IFERROR(INDEX(Accounts!$B$2:$B$24,MATCH(O38,Accounts!$A$2:$A$24,0)),"Unknown")) | I38: =IF(P38="","",IFERROR(INDEX(Categories!$B$2:$B$25,MATCH(P38,Categories!$A$2:$A$25,0)),"Unknown")) | J38: =IF(Q38="","",IFERROR(INDEX(Accounts!$B$2:$B$24,MATCH(Q38,Accounts!$A$2:$A$24,0)),"Unknown")) | K38: =IF(R38="","",IFERROR(INDEX(Accounts!$B$2:$B$24,MATCH(R38,Accounts!$A$2:$A$24,0)),"Unknown")) | L38: =IF(S38="","",IFERROR(INDEX(People!$B$2:$B$7,MATCH(S38,People!$A$2:$A$7,0)),"Unknown")) | M38: =IF(T38="","",IFERROR(INDEX(Recurrings!$B$2:$B$3,MATCH(T38,Recurrings!$A$2:$A$3,0)),"Unknown")) | N38: =IF(U38="","",IFERROR(INDEX(Users!$B$2:$B$2,MATCH(U38,Users!$A$2:$A$2,0)),"Unknown")) | O38: 88892af2-1b81-4798-904f-38a863b1aa57 | P38: d1a09f78-95d2-4fb3-9dd1-1ae8a33fa3d8 | U38: 814248de-0f8d-4712-bd00-91d12164a414
A39: 40 | B39: Sabji | C39: 230 | D39: Expense | E39: 2026-07-06T21:34:54.020 | F39: 2026-07-26T02:48:42.045 | H39: =IF(O39="","",IFERROR(INDEX(Accounts!$B$2:$B$24,MATCH(O39,Accounts!$A$2:$A$24,0)),"Unknown")) | I39: =IF(P39="","",IFERROR(INDEX(Categories!$B$2:$B$25,MATCH(P39,Categories!$A$2:$A$25,0)),"Unknown")) | J39: =IF(Q39="","",IFERROR(INDEX(Accounts!$B$2:$B$24,MATCH(Q39,Accounts!$A$2:$A$24,0)),"Unknown")) | K39: =IF(R39="","",IFERROR(INDEX(Accounts!$B$2:$B$24,MATCH(R39,Accounts!$A$2:$A$24,0)),"Unknown")) | L39: =IF(S39="","",IFERROR(INDEX(People!$B$2:$B$7,MATCH(S39,People!$A$2:$A$7,0)),"Unknown")) | M39: =IF(T39="","",IFERROR(INDEX(Recurrings!$B$2:$B$3,MATCH(T39,Recurrings!$A$2:$A$3,0)),"Unknown")) | N39: =IF(U39="","",IFERROR(INDEX(Users!$B$2:$B$2,MATCH(U39,Users!$A$2:$A$2,0)),"Unknown")) | O39: 8cedd8c1-7bcb-4b94-be6b-e72b888f1084 | P39: 066d9d96-53ec-4eb7-a045-fc8dfb1d33cb | S39: 7214a9a0-5619-49f8-8521-181d4faf1190 | U39: 814248de-0f8d-4712-bd00-91d12164a414
A40: 41 | B40: Water | C40: 30 | D40: Expense | E40: 2026-07-06T21:37:47.042 | F40: 2026-07-26T02:49:51.200 | H40: =IF(O40="","",IFERROR(INDEX(Accounts!$B$2:$B$24,MATCH(O40,Accounts!$A$2:$A$24,0)),"Unknown")) | I40: =IF(P40="","",IFERROR(INDEX(Categories!$B$2:$B$25,MATCH(P40,Categories!$A$2:$A$25,0)),"Unknown")) | J40: =IF(Q40="","",IFERROR(INDEX(Accounts!$B$2:$B$24,MATCH(Q40,Accounts!$A$2:$A$24,0)),"Unknown")) | K40: =IF(R40="","",IFERROR(INDEX(Accounts!$B$2:$B$24,MATCH(R40,Accounts!$A$2:$A$24,0)),"Unknown")) | L40: =IF(S40="","",IFERROR(INDEX(People!$B$2:$B$7,MATCH(S40,People!$A$2:$A$7,0)),"Unknown")) | M40: =IF(T40="","",IFERROR(INDEX(Recurrings!$B$2:$B$3,MATCH(T40,Recurrings!$A$2:$A$3,0)),"Unknown")) | N40: =IF(U40="","",IFERROR(INDEX(Users!$B$2:$B$2,MATCH(U40,Users!$A$2:$A$2,0)),"Unknown")) | O40: 183283c7-9ae3-49e4-ae84-a5364bc337ea | P40: b5eb22d9-3779-43fc-99af-eded3ff9bcd8 | S40: 7214a9a0-5619-49f8-8521-181d4faf1190 | U40: 814248de-0f8d-4712-bd00-91d12164a414
A41: 42 | B41: Expense | C41: 50 | D41: Expense | E41: 2026-07-06T00:09:22.000 | F41: 2026-07-26T02:47:37.201 | H41: =IF(O41="","",IFERROR(INDEX(Accounts!$B$2:$B$24,MATCH(O41,Accounts!$A$2:$A$24,0)),"Unknown")) | I41: =IF(P41="","",IFERROR(INDEX(Categories!$B$2:$B$25,MATCH(P41,Categories!$A$2:$A$25,0)),"Unknown")) | J41: =IF(Q41="","",IFERROR(INDEX(Accounts!$B$2:$B$24,MATCH(Q41,Accounts!$A$2:$A$24,0)),"Unknown")) | K41: =IF(R41="","",IFERROR(INDEX(Accounts!$B$2:$B$24,MATCH(R41,Accounts!$A$2:$A$24,0)),"Unknown")) | L41: =IF(S41="","",IFERROR(INDEX(People!$B$2:$B$7,MATCH(S41,People!$A$2:$A$7,0)),"Unknown")) | M41: =IF(T41="","",IFERROR(INDEX(Recurrings!$B$2:$B$3,MATCH(T41,Recurrings!$A$2:$A$3,0)),"Unknown")) | N41: =IF(U41="","",IFERROR(INDEX(Users!$B$2:$B$2,MATCH(U41,Users!$A$2:$A$2,0)),"Unknown")) | O41: 18110823-8fe5-4547-b1d3-8dbd2cc5b2e3 | P41: 892419eb-083b-410f-b146-1f3c70914aa1 | S41: ca7539c0-14da-430a-ae59-44fee8b96222 | U41: 814248de-0f8d-4712-bd00-91d12164a414
A42: 43 | B42: Rain coat | C42: 1110 | D42: Expense | E42: 2026-07-06T00:26:08.000 | F42: 2026-07-26T02:49:40.736 | H42: =IF(O42="","",IFERROR(INDEX(Accounts!$B$2:$B$24,MATCH(O42,Accounts!$A$2:$A$24,0)),"Unknown")) | I42: =IF(P42="","",IFERROR(INDEX(Categories!$B$2:$B$25,MATCH(P42,Categories!$A$2:$A$25,0)),"Unknown")) | J42: =IF(Q42="","",IFERROR(INDEX(Accounts!$B$2:$B$24,MATCH(Q42,Accounts!$A$2:$A$24,0)),"Unknown")) | K42: =IF(R42="","",IFERROR(INDEX(Accounts!$B$2:$B$24,MATCH(R42,Accounts!$A$2:$A$24,0)),"Unknown")) | L42: =IF(S42="","",IFERROR(INDEX(People!$B$2:$B$7,MATCH(S42,People!$A$2:$A$7,0)),"Unknown")) | M42: =IF(T42="","",IFERROR(INDEX(Recurrings!$B$2:$B$3,MATCH(T42,Recurrings!$A$2:$A$3,0)),"Unknown")) | N42: =IF(U42="","",IFERROR(INDEX(Users!$B$2:$B$2,MATCH(U42,Users!$A$2:$A$2,0)),"Unknown")) | O42: 183283c7-9ae3-49e4-ae84-a5364bc337ea | P42: d1a09f78-95d2-4fb3-9dd1-1ae8a33fa3d8 | S42: 7214a9a0-5619-49f8-8521-181d4faf1190 | U42: 814248de-0f8d-4712-bd00-91d12164a414
A43: 44 | B43: Mib recharge gautam | C43: 298 | D43: Expense | E43: 2026-07-07T11:09:59.821 | F43: 2026-07-07T11:09:59.821 | H43: =IF(O43="","",IFERROR(INDEX(Accounts!$B$2:$B$24,MATCH(O43,Accounts!$A$2:$A$24,0)),"Unknown")) | I43: =IF(P43="","",IFERROR(INDEX(Categories!$B$2:$B$25,MATCH(P43,Categories!$A$2:$A$25,0)),"Unknown")) | J43: =IF(Q43="","",IFERROR(INDEX(Accounts!$B$2:$B$24,MATCH(Q43,Accounts!$A$2:$A$24,0)),"Unknown")) | K43: =IF(R43="","",IFERROR(INDEX(Accounts!$B$2:$B$24,MATCH(R43,Accounts!$A$2:$A$24,0)),"Unknown")) | L43: =IF(S43="","",IFERROR(INDEX(People!$B$2:$B$7,MATCH(S43,People!$A$2:$A$7,0)),"Unknown")) | M43: =IF(T43="","",IFERROR(INDEX(Recurrings!$B$2:$B$3,MATCH(T43,Recurrings!$A$2:$A$3,0)),"Unknown")) | N43: =IF(U43="","",IFERROR(INDEX(Users!$B$2:$B$2,MATCH(U43,Users!$A$2:$A$2,0)),"Unknown")) | O43: a5b44f57-40f5-4b0e-96db-1179f20d75d0 | P43: 892419eb-083b-410f-b146-1f3c70914aa1 | U43: 814248de-0f8d-4712-bd00-91d12164a414
A44: 45 | C44: 200000 | D44: Transfer | E44: 2026-07-04T11:10:04.000 | F44: 2026-07-08T15:32:07.040 | H44: =IF(O44="","",IFERROR(INDEX(Accounts!$B$2:$B$24,MATCH(O44,Accounts!$A$2:$A$24,0)),"Unknown")) | I44: =IF(P44="","",IFERROR(INDEX(Categories!$B$2:$B$25,MATCH(P44,Categories!$A$2:$A$25,0)),"Unknown")) | J44: =IF(Q44="","",IFERROR(INDEX(Accounts!$B$2:$B$24,MATCH(Q44,Accounts!$A$2:$A$24,0)),"Unknown")) | K44: =IF(R44="","",IFERROR(INDEX(Accounts!$B$2:$B$24,MATCH(R44,Accounts!$A$2:$A$24,0)),"Unknown")) | L44: =IF(S44="","",IFERROR(INDEX(People!$B$2:$B$7,MATCH(S44,People!$A$2:$A$7,0)),"Unknown")) | M44: =IF(T44="","",IFERROR(INDEX(Recurrings!$B$2:$B$3,MATCH(T44,Recurrings!$A$2:$A$3,0)),"Unknown")) | N44: =IF(U44="","",IFERROR(INDEX(Users!$B$2:$B$2,MATCH(U44,Users!$A$2:$A$2,0)),"Unknown")) | Q44: a5b44f57-40f5-4b0e-96db-1179f20d75d0 | R44: 2b9af0c9-8855-4666-9be1-4c781d9f1ec3 | U44: 814248de-0f8d-4712-bd00-91d12164a414
A45: 46 | B45: 6th july bill | C45: 130 | D45: Income | E45: 2026-07-07T12:25:17.455 | F45: 2026-07-17T14:47:19.474 | H45: =IF(O45="","",IFERROR(INDEX(Accounts!$B$2:$B$24,MATCH(O45,Accounts!$A$2:$A$24,0)),"Unknown")) | I45: =IF(P45="","",IFERROR(INDEX(Categories!$B$2:$B$25,MATCH(P45,Categories!$A$2:$A$25,0)),"Unknown")) | J45: =IF(Q45="","",IFERROR(INDEX(Accounts!$B$2:$B$24,MATCH(Q45,Accounts!$A$2:$A$24,0)),"Unknown")) | K45: =IF(R45="","",IFERROR(INDEX(Accounts!$B$2:$B$24,MATCH(R45,Accounts!$A$2:$A$24,0)),"Unknown")) | L45: =IF(S45="","",IFERROR(INDEX(People!$B$2:$B$7,MATCH(S45,People!$A$2:$A$7,0)),"Unknown")) | M45: =IF(T45="","",IFERROR(INDEX(Recurrings!$B$2:$B$3,MATCH(T45,Recurrings!$A$2:$A$3,0)),"Unknown")) | N45: =IF(U45="","",IFERROR(INDEX(Users!$B$2:$B$2,MATCH(U45,Users!$A$2:$A$2,0)),"Unknown")) | O45: 7aeb233a-f5a8-4242-9a4a-0b401a7cf99b | P45: e437a0b5-5f69-4f5b-b879-b8de520215cc | U45: 814248de-0f8d-4712-bd00-91d12164a414
A46: 47 | B46: Lunch | C46: 80 | D46: Expense | E46: 2026-07-07T13:28:56.892 | F46: 2026-07-07T13:28:56.892 | H46: =IF(O46="","",IFERROR(INDEX(Accounts!$B$2:$B$24,MATCH(O46,Accounts!$A$2:$A$24,0)),"Unknown")) | I46: =IF(P46="","",IFERROR(INDEX(Categories!$B$2:$B$25,MATCH(P46,Categories!$A$2:$A$25,0)),"Unknown")) | J46: =IF(Q46="","",IFERROR(INDEX(Accounts!$B$2:$B$24,MATCH(Q46,Accounts!$A$2:$A$24,0)),"Unknown")) | K46: =IF(R46="","",IFERROR(INDEX(Accounts!$B$2:$B$24,MATCH(R46,Accounts!$A$2:$A$24,0)),"Unknown")) | L46: =IF(S46="","",IFERROR(INDEX(People!$B$2:$B$7,MATCH(S46,People!$A$2:$A$7,0)),"Unknown")) | M46: =IF(T46="","",IFERROR(INDEX(Recurrings!$B$2:$B$3,MATCH(T46,Recurrings!$A$2:$A$3,0)),"Unknown")) | N46: =IF(U46="","",IFERROR(INDEX(Users!$B$2:$B$2,MATCH(U46,Users!$A$2:$A$2,0)),"Unknown")) | O46: a5b44f57-40f5-4b0e-96db-1179f20d75d0 | P46: 9ea0a2b1-4b22-40a4-81ab-843452f9c274 | U46: 814248de-0f8d-4712-bd00-91d12164a414
A47: 48 | B47: Office fare | C47: 27 | D47: Expense | E47: 2026-07-07T19:59:35.741 | F47: 2026-07-07T19:59:35.741 | H47: =IF(O47="","",IFERROR(INDEX(Accounts!$B$2:$B$24,MATCH(O47,Accounts!$A$2:$A$24,0)),"Unknown")) | I47: =IF(P47="","",IFERROR(INDEX(Categories!$B$2:$B$25,MATCH(P47,Categories!$A$2:$A$25,0)),"Unknown")) | J47: =IF(Q47="","",IFERROR(INDEX(Accounts!$B$2:$B$24,MATCH(Q47,Accounts!$A$2:$A$24,0)),"Unknown")) | K47: =IF(R47="","",IFERROR(INDEX(Accounts!$B$2:$B$24,MATCH(R47,Accounts!$A$2:$A$24,0)),"Unknown")) | L47: =IF(S47="","",IFERROR(INDEX(People!$B$2:$B$7,MATCH(S47,People!$A$2:$A$7,0)),"Unknown")) | M47: =IF(T47="","",IFERROR(INDEX(Recurrings!$B$2:$B$3,MATCH(T47,Recurrings!$A$2:$A$3,0)),"Unknown")) | N47: =IF(U47="","",IFERROR(INDEX(Users!$B$2:$B$2,MATCH(U47,Users!$A$2:$A$2,0)),"Unknown")) | O47: 7f7a9ca8-7be5-4ea0-811a-63e598d2c6d3 | P47: 59cb1d7a-195c-4fef-b7e6-682eb97de8a7 | U47: 814248de-0f8d-4712-bd00-91d12164a414
A48: 49 | B48: Ration | C48: 1230 | D48: Expense | E48: 2026-07-07T22:45:57.210 | F48: 2026-07-26T02:48:47.022 | H48: =IF(O48="","",IFERROR(INDEX(Accounts!$B$2:$B$24,MATCH(O48,Accounts!$A$2:$A$24,0)),"Unknown")) | I48: =IF(P48="","",IFERROR(INDEX(Categories!$B$2:$B$25,MATCH(P48,Categories!$A$2:$A$25,0)),"Unknown")) | J48: =IF(Q48="","",IFERROR(INDEX(Accounts!$B$2:$B$24,MATCH(Q48,Accounts!$A$2:$A$24,0)),"Unknown")) | K48: =IF(R48="","",IFERROR(INDEX(Accounts!$B$2:$B$24,MATCH(R48,Accounts!$A$2:$A$24,0)),"Unknown")) | L48: =IF(S48="","",IFERROR(INDEX(People!$B$2:$B$7,MATCH(S48,People!$A$2:$A$7,0)),"Unknown")) | M48: =IF(T48="","",IFERROR(INDEX(Recurrings!$B$2:$B$3,MATCH(T48,Recurrings!$A$2:$A$3,0)),"Unknown")) | N48: =IF(U48="","",IFERROR(INDEX(Users!$B$2:$B$2,MATCH(U48,Users!$A$2:$A$2,0)),"Unknown")) | O48: 8cedd8c1-7bcb-4b94-be6b-e72b888f1084 | P48: 066d9d96-53ec-4eb7-a045-fc8dfb1d33cb | S48: 7214a9a0-5619-49f8-8521-181d4faf1190 | U48: 814248de-0f8d-4712-bd00-91d12164a414
A49: 50 | B49: Expense | C49: 15 | D49: Expense | E49: 2026-07-07T23:45:03.679 | F49: 2026-07-26T02:47:44.393 | H49: =IF(O49="","",IFERROR(INDEX(Accounts!$B$2:$B$24,MATCH(O49,Accounts!$A$2:$A$24,0)),"Unknown")) | I49: =IF(P49="","",IFERROR(INDEX(Categories!$B$2:$B$25,MATCH(P49,Categories!$A$2:$A$25,0)),"Unknown")) | J49: =IF(Q49="","",IFERROR(INDEX(Accounts!$B$2:$B$24,MATCH(Q49,Accounts!$A$2:$A$24,0)),"Unknown")) | K49: =IF(R49="","",IFERROR(INDEX(Accounts!$B$2:$B$24,MATCH(R49,Accounts!$A$2:$A$24,0)),"Unknown")) | L49: =IF(S49="","",IFERROR(INDEX(People!$B$2:$B$7,MATCH(S49,People!$A$2:$A$7,0)),"Unknown")) | M49: =IF(T49="","",IFERROR(INDEX(Recurrings!$B$2:$B$3,MATCH(T49,Recurrings!$A$2:$A$3,0)),"Unknown")) | N49: =IF(U49="","",IFERROR(INDEX(Users!$B$2:$B$2,MATCH(U49,Users!$A$2:$A$2,0)),"Unknown")) | O49: 18110823-8fe5-4547-b1d3-8dbd2cc5b2e3 | P49: b5eb22d9-3779-43fc-99af-eded3ff9bcd8 | S49: ca7539c0-14da-430a-ae59-44fee8b96222 | U49: 814248de-0f8d-4712-bd00-91d12164a414
A50: 51 | B50: Office Transport Leverage | C50: 200 | D50: Income | E50: 2026-07-07T20:44:45.223 | F50: 2026-07-07T23:45:15.256 | H50: =IF(O50="","",IFERROR(INDEX(Accounts!$B$2:$B$24,MATCH(O50,Accounts!$A$2:$A$24,0)),"Unknown")) | I50: =IF(P50="","",IFERROR(INDEX(Categories!$B$2:$B$25,MATCH(P50,Categories!$A$2:$A$25,0)),"Unknown")) | J50: =IF(Q50="","",IFERROR(INDEX(Accounts!$B$2:$B$24,MATCH(Q50,Accounts!$A$2:$A$24,0)),"Unknown")) | K50: =IF(R50="","",IFERROR(INDEX(Accounts!$B$2:$B$24,MATCH(R50,Accounts!$A$2:$A$24,0)),"Unknown")) | L50: =IF(S50="","",IFERROR(INDEX(People!$B$2:$B$7,MATCH(S50,People!$A$2:$A$7,0)),"Unknown")) | M50: =IF(T50="","",IFERROR(INDEX(Recurrings!$B$2:$B$3,MATCH(T50,Recurrings!$A$2:$A$3,0)),"Unknown")) | N50: =IF(U50="","",IFERROR(INDEX(Users!$B$2:$B$2,MATCH(U50,Users!$A$2:$A$2,0)),"Unknown")) | O50: f89518bd-b7d1-4658-9692-994af79cfcb8 | P50: f894a6a7-dfc4-4c79-bf71-b2526dc474ac | T50: 5f717740-b341-4fec-9dee-eb1c70d3c260 | U50: 814248de-0f8d-4712-bd00-91d12164a414
A51: 52 | B51: Lunch | C51: 185 | D51: Expense | E51: 2026-07-08T12:58:51.830 | F51: 2026-07-08T12:58:51.830 | G51: Me and aniket | H51: =IF(O51="","",IFERROR(INDEX(Accounts!$B$2:$B$24,MATCH(O51,Accounts!$A$2:$A$24,0)),"Unknown")) | I51: =IF(P51="","",IFERROR(INDEX(Categories!$B$2:$B$25,MATCH(P51,Categories!$A$2:$A$25,0)),"Unknown")) | J51: =IF(Q51="","",IFERROR(INDEX(Accounts!$B$2:$B$24,MATCH(Q51,Accounts!$A$2:$A$24,0)),"Unknown")) | K51: =IF(R51="","",IFERROR(INDEX(Accounts!$B$2:$B$24,MATCH(R51,Accounts!$A$2:$A$24,0)),"Unknown")) | L51: =IF(S51="","",IFERROR(INDEX(People!$B$2:$B$7,MATCH(S51,People!$A$2:$A$7,0)),"Unknown")) | M51: =IF(T51="","",IFERROR(INDEX(Recurrings!$B$2:$B$3,MATCH(T51,Recurrings!$A$2:$A$3,0)),"Unknown")) | N51: =IF(U51="","",IFERROR(INDEX(Users!$B$2:$B$2,MATCH(U51,Users!$A$2:$A$2,0)),"Unknown")) | O51: aa69aba3-4e60-426d-adfa-15f984249883 | P51: 9ea0a2b1-4b22-40a4-81ab-843452f9c274 | U51: 814248de-0f8d-4712-bd00-91d12164a414
A52: 53 | B52: Aniket sutta | C52: 12 | D52: Expense | E52: 2026-07-08T13:29:58.389 | F52: 2026-07-08T13:29:58.389 | H52: =IF(O52="","",IFERROR(INDEX(Accounts!$B$2:$B$24,MATCH(O52,Accounts!$A$2:$A$24,0)),"Unknown")) | I52: =IF(P52="","",IFERROR(INDEX(Categories!$B$2:$B$25,MATCH(P52,Categories!$A$2:$A$25,0)),"Unknown")) | J52: =IF(Q52="","",IFERROR(INDEX(Accounts!$B$2:$B$24,MATCH(Q52,Accounts!$A$2:$A$24,0)),"Unknown")) | K52: =IF(R52="","",IFERROR(INDEX(Accounts!$B$2:$B$24,MATCH(R52,Accounts!$A$2:$A$24,0)),"Unknown")) | L52: =IF(S52="","",IFERROR(INDEX(People!$B$2:$B$7,MATCH(S52,People!$A$2:$A$7,0)),"Unknown")) | M52: =IF(T52="","",IFERROR(INDEX(Recurrings!$B$2:$B$3,MATCH(T52,Recurrings!$A$2:$A$3,0)),"Unknown")) | N52: =IF(U52="","",IFERROR(INDEX(Users!$B$2:$B$2,MATCH(U52,Users!$A$2:$A$2,0)),"Unknown")) | O52: 4b9fa03c-eddf-42ff-8d5f-eaa9e3086ce0 | P52: b5eb22d9-3779-43fc-99af-eded3ff9bcd8 | U52: 814248de-0f8d-4712-bd00-91d12164a414
A53: 54 | B53: From aniket | C53: 112 | D53: Income | E53: 2026-07-08T15:31:28.968 | F53: 2026-07-08T15:31:28.968 | G53: I spent on his lunch | H53: =IF(O53="","",IFERROR(INDEX(Accounts!$B$2:$B$24,MATCH(O53,Accounts!$A$2:$A$24,0)),"Unknown")) | I53: =IF(P53="","",IFERROR(INDEX(Categories!$B$2:$B$25,MATCH(P53,Categories!$A$2:$A$25,0)),"Unknown")) | J53: =IF(Q53="","",IFERROR(INDEX(Accounts!$B$2:$B$24,MATCH(Q53,Accounts!$A$2:$A$24,0)),"Unknown")) | K53: =IF(R53="","",IFERROR(INDEX(Accounts!$B$2:$B$24,MATCH(R53,Accounts!$A$2:$A$24,0)),"Unknown")) | L53: =IF(S53="","",IFERROR(INDEX(People!$B$2:$B$7,MATCH(S53,People!$A$2:$A$7,0)),"Unknown")) | M53: =IF(T53="","",IFERROR(INDEX(Recurrings!$B$2:$B$3,MATCH(T53,Recurrings!$A$2:$A$3,0)),"Unknown")) | N53: =IF(U53="","",IFERROR(INDEX(Users!$B$2:$B$2,MATCH(U53,Users!$A$2:$A$2,0)),"Unknown")) | O53: 4b9fa03c-eddf-42ff-8d5f-eaa9e3086ce0 | P53: 1c612037-9067-4e69-aebc-14619b77b363 | U53: 814248de-0f8d-4712-bd00-91d12164a414
A54: 55 | B54: Office Transport Leverage | C54: 200 | D54: Income | E54: 2026-07-08T20:44:45.223 | F54: 2026-07-08T15:36:18.890 | H54: =IF(O54="","",IFERROR(INDEX(Accounts!$B$2:$B$24,MATCH(O54,Accounts!$A$2:$A$24,0)),"Unknown")) | I54: =IF(P54="","",IFERROR(INDEX(Categories!$B$2:$B$25,MATCH(P54,Categories!$A$2:$A$25,0)),"Unknown")) | J54: =IF(Q54="","",IFERROR(INDEX(Accounts!$B$2:$B$24,MATCH(Q54,Accounts!$A$2:$A$24,0)),"Unknown")) | K54: =IF(R54="","",IFERROR(INDEX(Accounts!$B$2:$B$24,MATCH(R54,Accounts!$A$2:$A$24,0)),"Unknown")) | L54: =IF(S54="","",IFERROR(INDEX(People!$B$2:$B$7,MATCH(S54,People!$A$2:$A$7,0)),"Unknown")) | M54: =IF(T54="","",IFERROR(INDEX(Recurrings!$B$2:$B$3,MATCH(T54,Recurrings!$A$2:$A$3,0)),"Unknown")) | N54: =IF(U54="","",IFERROR(INDEX(Users!$B$2:$B$2,MATCH(U54,Users!$A$2:$A$2,0)),"Unknown")) | O54: f89518bd-b7d1-4658-9692-994af79cfcb8 | P54: f894a6a7-dfc4-4c79-bf71-b2526dc474ac | T54: 5f717740-b341-4fec-9dee-eb1c70d3c260 | U54: 814248de-0f8d-4712-bd00-91d12164a414
A55: 56 | B55: Snacks | C55: 130 | D55: Income | E55: 2026-07-08T15:44:29.259 | F55: 2026-07-17T14:47:15.521 | G55: Bill for 7th july | H55: =IF(O55="","",IFERROR(INDEX(Accounts!$B$2:$B$24,MATCH(O55,Accounts!$A$2:$A$24,0)),"Unknown")) | I55: =IF(P55="","",IFERROR(INDEX(Categories!$B$2:$B$25,MATCH(P55,Categories!$A$2:$A$25,0)),"Unknown")) | J55: =IF(Q55="","",IFERROR(INDEX(Accounts!$B$2:$B$24,MATCH(Q55,Accounts!$A$2:$A$24,0)),"Unknown")) | K55: =IF(R55="","",IFERROR(INDEX(Accounts!$B$2:$B$24,MATCH(R55,Accounts!$A$2:$A$24,0)),"Unknown")) | L55: =IF(S55="","",IFERROR(INDEX(People!$B$2:$B$7,MATCH(S55,People!$A$2:$A$7,0)),"Unknown")) | M55: =IF(T55="","",IFERROR(INDEX(Recurrings!$B$2:$B$3,MATCH(T55,Recurrings!$A$2:$A$3,0)),"Unknown")) | N55: =IF(U55="","",IFERROR(INDEX(Users!$B$2:$B$2,MATCH(U55,Users!$A$2:$A$2,0)),"Unknown")) | O55: 7aeb233a-f5a8-4242-9a4a-0b401a7cf99b | P55: e437a0b5-5f69-4f5b-b879-b8de520215cc | U55: 814248de-0f8d-4712-bd00-91d12164a414
A56: 57 | B56: Expense | C56: 310 | D56: Expense | E56: 2026-07-08T22:22:09.790 | F56: 2026-07-08T22:22:09.790 | H56: =IF(O56="","",IFERROR(INDEX(Accounts!$B$2:$B$24,MATCH(O56,Accounts!$A$2:$A$24,0)),"Unknown")) | I56: =IF(P56="","",IFERROR(INDEX(Categories!$B$2:$B$25,MATCH(P56,Categories!$A$2:$A$25,0)),"Unknown")) | J56: =IF(Q56="","",IFERROR(INDEX(Accounts!$B$2:$B$24,MATCH(Q56,Accounts!$A$2:$A$24,0)),"Unknown")) | K56: =IF(R56="","",IFERROR(INDEX(Accounts!$B$2:$B$24,MATCH(R56,Accounts!$A$2:$A$24,0)),"Unknown")) | L56: =IF(S56="","",IFERROR(INDEX(People!$B$2:$B$7,MATCH(S56,People!$A$2:$A$7,0)),"Unknown")) | M56: =IF(T56="","",IFERROR(INDEX(Recurrings!$B$2:$B$3,MATCH(T56,Recurrings!$A$2:$A$3,0)),"Unknown")) | N56: =IF(U56="","",IFERROR(INDEX(Users!$B$2:$B$2,MATCH(U56,Users!$A$2:$A$2,0)),"Unknown")) | O56: 183283c7-9ae3-49e4-ae84-a5364bc337ea | P56: 892419eb-083b-410f-b146-1f3c70914aa1 | S56: 7214a9a0-5619-49f8-8521-181d4faf1190 | U56: 814248de-0f8d-4712-bd00-91d12164a414
A57: 58 | B57: Expense | C57: 50 | D57: Expense | E57: 2026-07-08T22:22:25.225 | F57: 2026-07-08T22:22:25.225 | H57: =IF(O57="","",IFERROR(INDEX(Accounts!$B$2:$B$24,MATCH(O57,Accounts!$A$2:$A$24,0)),"Unknown")) | I57: =IF(P57="","",IFERROR(INDEX(Categories!$B$2:$B$25,MATCH(P57,Categories!$A$2:$A$25,0)),"Unknown")) | J57: =IF(Q57="","",IFERROR(INDEX(Accounts!$B$2:$B$24,MATCH(Q57,Accounts!$A$2:$A$24,0)),"Unknown")) | K57: =IF(R57="","",IFERROR(INDEX(Accounts!$B$2:$B$24,MATCH(R57,Accounts!$A$2:$A$24,0)),"Unknown")) | L57: =IF(S57="","",IFERROR(INDEX(People!$B$2:$B$7,MATCH(S57,People!$A$2:$A$7,0)),"Unknown")) | M57: =IF(T57="","",IFERROR(INDEX(Recurrings!$B$2:$B$3,MATCH(T57,Recurrings!$A$2:$A$3,0)),"Unknown")) | N57: =IF(U57="","",IFERROR(INDEX(Users!$B$2:$B$2,MATCH(U57,Users!$A$2:$A$2,0)),"Unknown")) | O57: 8cedd8c1-7bcb-4b94-be6b-e72b888f1084 | P57: 892419eb-083b-410f-b146-1f3c70914aa1 | S57: 7214a9a0-5619-49f8-8521-181d4faf1190 | U57: 814248de-0f8d-4712-bd00-91d12164a414
A58: 59 | B58: Expense | C58: 180 | D58: Expense | E58: 2026-07-08T23:20:52.180 | F58: 2026-07-08T23:20:52.180 | H58: =IF(O58="","",IFERROR(INDEX(Accounts!$B$2:$B$24,MATCH(O58,Accounts!$A$2:$A$24,0)),"Unknown")) | I58: =IF(P58="","",IFERROR(INDEX(Categories!$B$2:$B$25,MATCH(P58,Categories!$A$2:$A$25,0)),"Unknown")) | J58: =IF(Q58="","",IFERROR(INDEX(Accounts!$B$2:$B$24,MATCH(Q58,Accounts!$A$2:$A$24,0)),"Unknown")) | K58: =IF(R58="","",IFERROR(INDEX(Accounts!$B$2:$B$24,MATCH(R58,Accounts!$A$2:$A$24,0)),"Unknown")) | L58: =IF(S58="","",IFERROR(INDEX(People!$B$2:$B$7,MATCH(S58,People!$A$2:$A$7,0)),"Unknown")) | M58: =IF(T58="","",IFERROR(INDEX(Recurrings!$B$2:$B$3,MATCH(T58,Recurrings!$A$2:$A$3,0)),"Unknown")) | N58: =IF(U58="","",IFERROR(INDEX(Users!$B$2:$B$2,MATCH(U58,Users!$A$2:$A$2,0)),"Unknown")) | O58: 18110823-8fe5-4547-b1d3-8dbd2cc5b2e3 | P58: 892419eb-083b-410f-b146-1f3c70914aa1 | S58: ca7539c0-14da-430a-ae59-44fee8b96222 | U58: 814248de-0f8d-4712-bd00-91d12164a414
A59: 60 | B59: Snacks | C59: 130 | D59: Income | E59: 2026-07-09T12:33:45.609 | F59: 2026-07-17T14:47:10.437 | G59: Bill for 8th july | H59: =IF(O59="","",IFERROR(INDEX(Accounts!$B$2:$B$24,MATCH(O59,Accounts!$A$2:$A$24,0)),"Unknown")) | I59: =IF(P59="","",IFERROR(INDEX(Categories!$B$2:$B$25,MATCH(P59,Categories!$A$2:$A$25,0)),"Unknown")) | J59: =IF(Q59="","",IFERROR(INDEX(Accounts!$B$2:$B$24,MATCH(Q59,Accounts!$A$2:$A$24,0)),"Unknown")) | K59: =IF(R59="","",IFERROR(INDEX(Accounts!$B$2:$B$24,MATCH(R59,Accounts!$A$2:$A$24,0)),"Unknown")) | L59: =IF(S59="","",IFERROR(INDEX(People!$B$2:$B$7,MATCH(S59,People!$A$2:$A$7,0)),"Unknown")) | M59: =IF(T59="","",IFERROR(INDEX(Recurrings!$B$2:$B$3,MATCH(T59,Recurrings!$A$2:$A$3,0)),"Unknown")) | N59: =IF(U59="","",IFERROR(INDEX(Users!$B$2:$B$2,MATCH(U59,Users!$A$2:$A$2,0)),"Unknown")) | O59: 7aeb233a-f5a8-4242-9a4a-0b401a7cf99b | P59: e437a0b5-5f69-4f5b-b879-b8de520215cc | S59: a86797b7-3cdf-415f-b4ea-16b33ec6d09d | U59: 814248de-0f8d-4712-bd00-91d12164a414
A60: 61 | B60: Office Transport Leverage | C60: 200 | D60: Income | E60: 2026-07-09T20:44:45.223 | F60: 2026-07-09T12:34:04.851 | H60: =IF(O60="","",IFERROR(INDEX(Accounts!$B$2:$B$24,MATCH(O60,Accounts!$A$2:$A$24,0)),"Unknown")) | I60: =IF(P60="","",IFERROR(INDEX(Categories!$B$2:$B$25,MATCH(P60,Categories!$A$2:$A$25,0)),"Unknown")) | J60: =IF(Q60="","",IFERROR(INDEX(Accounts!$B$2:$B$24,MATCH(Q60,Accounts!$A$2:$A$24,0)),"Unknown")) | K60: =IF(R60="","",IFERROR(INDEX(Accounts!$B$2:$B$24,MATCH(R60,Accounts!$A$2:$A$24,0)),"Unknown")) | L60: =IF(S60="","",IFERROR(INDEX(People!$B$2:$B$7,MATCH(S60,People!$A$2:$A$7,0)),"Unknown")) | M60: =IF(T60="","",IFERROR(INDEX(Recurrings!$B$2:$B$3,MATCH(T60,Recurrings!$A$2:$A$3,0)),"Unknown")) | N60: =IF(U60="","",IFERROR(INDEX(Users!$B$2:$B$2,MATCH(U60,Users!$A$2:$A$2,0)),"Unknown")) | O60: f89518bd-b7d1-4658-9692-994af79cfcb8 | P60: f894a6a7-dfc4-4c79-bf71-b2526dc474ac | T60: 5f717740-b341-4fec-9dee-eb1c70d3c260 | U60: 814248de-0f8d-4712-bd00-91d12164a414
A61: 62 | B61: Lunch | C61: 84 | D61: Expense | E61: 2026-07-09T14:36:31.904 | F61: 2026-07-09T14:36:31.904 | H61: =IF(O61="","",IFERROR(INDEX(Accounts!$B$2:$B$24,MATCH(O61,Accounts!$A$2:$A$24,0)),"Unknown")) | I61: =IF(P61="","",IFERROR(INDEX(Categories!$B$2:$B$25,MATCH(P61,Categories!$A$2:$A$25,0)),"Unknown")) | J61: =IF(Q61="","",IFERROR(INDEX(Accounts!$B$2:$B$24,MATCH(Q61,Accounts!$A$2:$A$24,0)),"Unknown")) | K61: =IF(R61="","",IFERROR(INDEX(Accounts!$B$2:$B$24,MATCH(R61,Accounts!$A$2:$A$24,0)),"Unknown")) | L61: =IF(S61="","",IFERROR(INDEX(People!$B$2:$B$7,MATCH(S61,People!$A$2:$A$7,0)),"Unknown")) | M61: =IF(T61="","",IFERROR(INDEX(Recurrings!$B$2:$B$3,MATCH(T61,Recurrings!$A$2:$A$3,0)),"Unknown")) | N61: =IF(U61="","",IFERROR(INDEX(Users!$B$2:$B$2,MATCH(U61,Users!$A$2:$A$2,0)),"Unknown")) | O61: 4b9fa03c-eddf-42ff-8d5f-eaa9e3086ce0 | P61: 9ea0a2b1-4b22-40a4-81ab-843452f9c274 | U61: 814248de-0f8d-4712-bd00-91d12164a414
A62: 63 | B62: Sony earbuds c510n | C62: 2535 | D62: Expense | E62: 2026-07-09T16:29:40.469 | F62: 2026-07-09T16:29:40.469 | G62: For gautam | H62: =IF(O62="","",IFERROR(INDEX(Accounts!$B$2:$B$24,MATCH(O62,Accounts!$A$2:$A$24,0)),"Unknown")) | I62: =IF(P62="","",IFERROR(INDEX(Categories!$B$2:$B$25,MATCH(P62,Categories!$A$2:$A$25,0)),"Unknown")) | J62: =IF(Q62="","",IFERROR(INDEX(Accounts!$B$2:$B$24,MATCH(Q62,Accounts!$A$2:$A$24,0)),"Unknown")) | K62: =IF(R62="","",IFERROR(INDEX(Accounts!$B$2:$B$24,MATCH(R62,Accounts!$A$2:$A$24,0)),"Unknown")) | L62: =IF(S62="","",IFERROR(INDEX(People!$B$2:$B$7,MATCH(S62,People!$A$2:$A$7,0)),"Unknown")) | M62: =IF(T62="","",IFERROR(INDEX(Recurrings!$B$2:$B$3,MATCH(T62,Recurrings!$A$2:$A$3,0)),"Unknown")) | N62: =IF(U62="","",IFERROR(INDEX(Users!$B$2:$B$2,MATCH(U62,Users!$A$2:$A$2,0)),"Unknown")) | O62: 855f5acb-cf90-4eed-bef4-7733fec688b6 | P62: d1a09f78-95d2-4fb3-9dd1-1ae8a33fa3d8 | U62: 814248de-0f8d-4712-bd00-91d12164a414
A63: 64 | B63: Milk and biscuits | C63: 40 | D63: Expense | E63: 2026-07-09T19:01:56.565 | F63: 2026-07-09T19:01:56.565 | H63: =IF(O63="","",IFERROR(INDEX(Accounts!$B$2:$B$24,MATCH(O63,Accounts!$A$2:$A$24,0)),"Unknown")) | I63: =IF(P63="","",IFERROR(INDEX(Categories!$B$2:$B$25,MATCH(P63,Categories!$A$2:$A$25,0)),"Unknown")) | J63: =IF(Q63="","",IFERROR(INDEX(Accounts!$B$2:$B$24,MATCH(Q63,Accounts!$A$2:$A$24,0)),"Unknown")) | K63: =IF(R63="","",IFERROR(INDEX(Accounts!$B$2:$B$24,MATCH(R63,Accounts!$A$2:$A$24,0)),"Unknown")) | L63: =IF(S63="","",IFERROR(INDEX(People!$B$2:$B$7,MATCH(S63,People!$A$2:$A$7,0)),"Unknown")) | M63: =IF(T63="","",IFERROR(INDEX(Recurrings!$B$2:$B$3,MATCH(T63,Recurrings!$A$2:$A$3,0)),"Unknown")) | N63: =IF(U63="","",IFERROR(INDEX(Users!$B$2:$B$2,MATCH(U63,Users!$A$2:$A$2,0)),"Unknown")) | O63: 7f7a9ca8-7be5-4ea0-811a-63e598d2c6d3 | P63: 066d9d96-53ec-4eb7-a045-fc8dfb1d33cb | U63: 814248de-0f8d-4712-bd00-91d12164a414
A64: 65 | B64: Office fare | C64: 27 | D64: Expense | E64: 2026-07-09T19:02:16.180 | F64: 2026-07-09T19:02:16.180 | H64: =IF(O64="","",IFERROR(INDEX(Accounts!$B$2:$B$24,MATCH(O64,Accounts!$A$2:$A$24,0)),"Unknown")) | I64: =IF(P64="","",IFERROR(INDEX(Categories!$B$2:$B$25,MATCH(P64,Categories!$A$2:$A$25,0)),"Unknown")) | J64: =IF(Q64="","",IFERROR(INDEX(Accounts!$B$2:$B$24,MATCH(Q64,Accounts!$A$2:$A$24,0)),"Unknown")) | K64: =IF(R64="","",IFERROR(INDEX(Accounts!$B$2:$B$24,MATCH(R64,Accounts!$A$2:$A$24,0)),"Unknown")) | L64: =IF(S64="","",IFERROR(INDEX(People!$B$2:$B$7,MATCH(S64,People!$A$2:$A$7,0)),"Unknown")) | M64: =IF(T64="","",IFERROR(INDEX(Recurrings!$B$2:$B$3,MATCH(T64,Recurrings!$A$2:$A$3,0)),"Unknown")) | N64: =IF(U64="","",IFERROR(INDEX(Users!$B$2:$B$2,MATCH(U64,Users!$A$2:$A$2,0)),"Unknown")) | O64: 7f7a9ca8-7be5-4ea0-811a-63e598d2c6d3 | P64: 59cb1d7a-195c-4fef-b7e6-682eb97de8a7 | U64: 814248de-0f8d-4712-bd00-91d12164a414
A65: 66 | B65: Expense | C65: 310 | D65: Expense | E65: 2026-07-09T20:01:34.208 | F65: 2026-07-09T20:01:34.208 | H65: =IF(O65="","",IFERROR(INDEX(Accounts!$B$2:$B$24,MATCH(O65,Accounts!$A$2:$A$24,0)),"Unknown")) | I65: =IF(P65="","",IFERROR(INDEX(Categories!$B$2:$B$25,MATCH(P65,Categories!$A$2:$A$25,0)),"Unknown")) | J65: =IF(Q65="","",IFERROR(INDEX(Accounts!$B$2:$B$24,MATCH(Q65,Accounts!$A$2:$A$24,0)),"Unknown")) | K65: =IF(R65="","",IFERROR(INDEX(Accounts!$B$2:$B$24,MATCH(R65,Accounts!$A$2:$A$24,0)),"Unknown")) | L65: =IF(S65="","",IFERROR(INDEX(People!$B$2:$B$7,MATCH(S65,People!$A$2:$A$7,0)),"Unknown")) | M65: =IF(T65="","",IFERROR(INDEX(Recurrings!$B$2:$B$3,MATCH(T65,Recurrings!$A$2:$A$3,0)),"Unknown")) | N65: =IF(U65="","",IFERROR(INDEX(Users!$B$2:$B$2,MATCH(U65,Users!$A$2:$A$2,0)),"Unknown")) | O65: 8cedd8c1-7bcb-4b94-be6b-e72b888f1084 | P65: 892419eb-083b-410f-b146-1f3c70914aa1 | S65: 7214a9a0-5619-49f8-8521-181d4faf1190 | U65: 814248de-0f8d-4712-bd00-91d12164a414
A66: 67 | B66: Expense | C66: 210 | D66: Expense | E66: 2026-07-09T20:01:51.874 | F66: 2026-07-09T20:01:51.874 | H66: =IF(O66="","",IFERROR(INDEX(Accounts!$B$2:$B$24,MATCH(O66,Accounts!$A$2:$A$24,0)),"Unknown")) | I66: =IF(P66="","",IFERROR(INDEX(Categories!$B$2:$B$25,MATCH(P66,Categories!$A$2:$A$25,0)),"Unknown")) | J66: =IF(Q66="","",IFERROR(INDEX(Accounts!$B$2:$B$24,MATCH(Q66,Accounts!$A$2:$A$24,0)),"Unknown")) | K66: =IF(R66="","",IFERROR(INDEX(Accounts!$B$2:$B$24,MATCH(R66,Accounts!$A$2:$A$24,0)),"Unknown")) | L66: =IF(S66="","",IFERROR(INDEX(People!$B$2:$B$7,MATCH(S66,People!$A$2:$A$7,0)),"Unknown")) | M66: =IF(T66="","",IFERROR(INDEX(Recurrings!$B$2:$B$3,MATCH(T66,Recurrings!$A$2:$A$3,0)),"Unknown")) | N66: =IF(U66="","",IFERROR(INDEX(Users!$B$2:$B$2,MATCH(U66,Users!$A$2:$A$2,0)),"Unknown")) | O66: 183283c7-9ae3-49e4-ae84-a5364bc337ea | P66: 892419eb-083b-410f-b146-1f3c70914aa1 | S66: 7214a9a0-5619-49f8-8521-181d4faf1190 | U66: 814248de-0f8d-4712-bd00-91d12164a414
A67: 68 | B67: Expense | C67: 105 | D67: Expense | E67: 2026-07-09T23:29:48.536 | F67: 2026-07-09T23:29:48.536 | H67: =IF(O67="","",IFERROR(INDEX(Accounts!$B$2:$B$24,MATCH(O67,Accounts!$A$2:$A$24,0)),"Unknown")) | I67: =IF(P67="","",IFERROR(INDEX(Categories!$B$2:$B$25,MATCH(P67,Categories!$A$2:$A$25,0)),"Unknown")) | J67: =IF(Q67="","",IFERROR(INDEX(Accounts!$B$2:$B$24,MATCH(Q67,Accounts!$A$2:$A$24,0)),"Unknown")) | K67: =IF(R67="","",IFERROR(INDEX(Accounts!$B$2:$B$24,MATCH(R67,Accounts!$A$2:$A$24,0)),"Unknown")) | L67: =IF(S67="","",IFERROR(INDEX(People!$B$2:$B$7,MATCH(S67,People!$A$2:$A$7,0)),"Unknown")) | M67: =IF(T67="","",IFERROR(INDEX(Recurrings!$B$2:$B$3,MATCH(T67,Recurrings!$A$2:$A$3,0)),"Unknown")) | N67: =IF(U67="","",IFERROR(INDEX(Users!$B$2:$B$2,MATCH(U67,Users!$A$2:$A$2,0)),"Unknown")) | O67: 18110823-8fe5-4547-b1d3-8dbd2cc5b2e3 | P67: 892419eb-083b-410f-b146-1f3c70914aa1 | S67: ca7539c0-14da-430a-ae59-44fee8b96222 | U67: 814248de-0f8d-4712-bd00-91d12164a414
A68: 69 | B68: Snacks | C68: 130 | D68: Income | E68: 2026-07-10T15:11:35.956 | F68: 2026-07-17T14:47:04.688 | G68: Bill for 9th july | H68: =IF(O68="","",IFERROR(INDEX(Accounts!$B$2:$B$24,MATCH(O68,Accounts!$A$2:$A$24,0)),"Unknown")) | I68: =IF(P68="","",IFERROR(INDEX(Categories!$B$2:$B$25,MATCH(P68,Categories!$A$2:$A$25,0)),"Unknown")) | J68: =IF(Q68="","",IFERROR(INDEX(Accounts!$B$2:$B$24,MATCH(Q68,Accounts!$A$2:$A$24,0)),"Unknown")) | K68: =IF(R68="","",IFERROR(INDEX(Accounts!$B$2:$B$24,MATCH(R68,Accounts!$A$2:$A$24,0)),"Unknown")) | L68: =IF(S68="","",IFERROR(INDEX(People!$B$2:$B$7,MATCH(S68,People!$A$2:$A$7,0)),"Unknown")) | M68: =IF(T68="","",IFERROR(INDEX(Recurrings!$B$2:$B$3,MATCH(T68,Recurrings!$A$2:$A$3,0)),"Unknown")) | N68: =IF(U68="","",IFERROR(INDEX(Users!$B$2:$B$2,MATCH(U68,Users!$A$2:$A$2,0)),"Unknown")) | O68: 7aeb233a-f5a8-4242-9a4a-0b401a7cf99b | P68: e437a0b5-5f69-4f5b-b879-b8de520215cc | S68: e4d7649a-60df-4f0e-a26f-923f8c156122 | U68: 814248de-0f8d-4712-bd00-91d12164a414
A69: 70 | B69: Expense | C69: 80 | D69: Expense | E69: 2026-07-10T23:07:28.608 | F69: 2026-07-10T23:07:28.608 | H69: =IF(O69="","",IFERROR(INDEX(Accounts!$B$2:$B$24,MATCH(O69,Accounts!$A$2:$A$24,0)),"Unknown")) | I69: =IF(P69="","",IFERROR(INDEX(Categories!$B$2:$B$25,MATCH(P69,Categories!$A$2:$A$25,0)),"Unknown")) | J69: =IF(Q69="","",IFERROR(INDEX(Accounts!$B$2:$B$24,MATCH(Q69,Accounts!$A$2:$A$24,0)),"Unknown")) | K69: =IF(R69="","",IFERROR(INDEX(Accounts!$B$2:$B$24,MATCH(R69,Accounts!$A$2:$A$24,0)),"Unknown")) | L69: =IF(S69="","",IFERROR(INDEX(People!$B$2:$B$7,MATCH(S69,People!$A$2:$A$7,0)),"Unknown")) | M69: =IF(T69="","",IFERROR(INDEX(Recurrings!$B$2:$B$3,MATCH(T69,Recurrings!$A$2:$A$3,0)),"Unknown")) | N69: =IF(U69="","",IFERROR(INDEX(Users!$B$2:$B$2,MATCH(U69,Users!$A$2:$A$2,0)),"Unknown")) | O69: 18110823-8fe5-4547-b1d3-8dbd2cc5b2e3 | P69: 892419eb-083b-410f-b146-1f3c70914aa1 | S69: ca7539c0-14da-430a-ae59-44fee8b96222 | U69: 814248de-0f8d-4712-bd00-91d12164a414
A70: 71 | B70: Eggs | C70: 34 | D70: Expense | E70: 2026-07-11T23:15:36.144 | F70: 2026-07-11T23:15:36.144 | H70: =IF(O70="","",IFERROR(INDEX(Accounts!$B$2:$B$24,MATCH(O70,Accounts!$A$2:$A$24,0)),"Unknown")) | I70: =IF(P70="","",IFERROR(INDEX(Categories!$B$2:$B$25,MATCH(P70,Categories!$A$2:$A$25,0)),"Unknown")) | J70: =IF(Q70="","",IFERROR(INDEX(Accounts!$B$2:$B$24,MATCH(Q70,Accounts!$A$2:$A$24,0)),"Unknown")) | K70: =IF(R70="","",IFERROR(INDEX(Accounts!$B$2:$B$24,MATCH(R70,Accounts!$A$2:$A$24,0)),"Unknown")) | L70: =IF(S70="","",IFERROR(INDEX(People!$B$2:$B$7,MATCH(S70,People!$A$2:$A$7,0)),"Unknown")) | M70: =IF(T70="","",IFERROR(INDEX(Recurrings!$B$2:$B$3,MATCH(T70,Recurrings!$A$2:$A$3,0)),"Unknown")) | N70: =IF(U70="","",IFERROR(INDEX(Users!$B$2:$B$2,MATCH(U70,Users!$A$2:$A$2,0)),"Unknown")) | O70: 7f7a9ca8-7be5-4ea0-811a-63e598d2c6d3 | P70: 066d9d96-53ec-4eb7-a045-fc8dfb1d33cb | U70: 814248de-0f8d-4712-bd00-91d12164a414
A71: 72 | B71: Ghar bhara bdn | C71: 7500 | D71: Expense | E71: 2026-07-11T23:16:05.364 | F71: 2026-07-11T23:16:05.364 | H71: =IF(O71="","",IFERROR(INDEX(Accounts!$B$2:$B$24,MATCH(O71,Accounts!$A$2:$A$24,0)),"Unknown")) | I71: =IF(P71="","",IFERROR(INDEX(Categories!$B$2:$B$25,MATCH(P71,Categories!$A$2:$A$25,0)),"Unknown")) | J71: =IF(Q71="","",IFERROR(INDEX(Accounts!$B$2:$B$24,MATCH(Q71,Accounts!$A$2:$A$24,0)),"Unknown")) | K71: =IF(R71="","",IFERROR(INDEX(Accounts!$B$2:$B$24,MATCH(R71,Accounts!$A$2:$A$24,0)),"Unknown")) | L71: =IF(S71="","",IFERROR(INDEX(People!$B$2:$B$7,MATCH(S71,People!$A$2:$A$7,0)),"Unknown")) | M71: =IF(T71="","",IFERROR(INDEX(Recurrings!$B$2:$B$3,MATCH(T71,Recurrings!$A$2:$A$3,0)),"Unknown")) | N71: =IF(U71="","",IFERROR(INDEX(Users!$B$2:$B$2,MATCH(U71,Users!$A$2:$A$2,0)),"Unknown")) | O71: 183283c7-9ae3-49e4-ae84-a5364bc337ea | P71: 918ebcda-33fa-40b6-848d-95dd00f74bad | S71: 7214a9a0-5619-49f8-8521-181d4faf1190 | U71: 814248de-0f8d-4712-bd00-91d12164a414
A72: 73 | B72: Expense | C72: 290 | D72: Expense | E72: 2026-07-11T23:16:44.338 | F72: 2026-07-31T00:04:59.075 | H72: =IF(O72="","",IFERROR(INDEX(Accounts!$B$2:$B$24,MATCH(O72,Accounts!$A$2:$A$24,0)),"Unknown")) | I72: =IF(P72="","",IFERROR(INDEX(Categories!$B$2:$B$25,MATCH(P72,Categories!$A$2:$A$25,0)),"Unknown")) | J72: =IF(Q72="","",IFERROR(INDEX(Accounts!$B$2:$B$24,MATCH(Q72,Accounts!$A$2:$A$24,0)),"Unknown")) | K72: =IF(R72="","",IFERROR(INDEX(Accounts!$B$2:$B$24,MATCH(R72,Accounts!$A$2:$A$24,0)),"Unknown")) | L72: =IF(S72="","",IFERROR(INDEX(People!$B$2:$B$7,MATCH(S72,People!$A$2:$A$7,0)),"Unknown")) | M72: =IF(T72="","",IFERROR(INDEX(Recurrings!$B$2:$B$3,MATCH(T72,Recurrings!$A$2:$A$3,0)),"Unknown")) | N72: =IF(U72="","",IFERROR(INDEX(Users!$B$2:$B$2,MATCH(U72,Users!$A$2:$A$2,0)),"Unknown")) | O72: 8cedd8c1-7bcb-4b94-be6b-e72b888f1084 | P72: 892419eb-083b-410f-b146-1f3c70914aa1 | S72: 7214a9a0-5619-49f8-8521-181d4faf1190 | U72: 814248de-0f8d-4712-bd00-91d12164a414
A73: 74 | B73: Amazon shopping | C73: 3003 | D73: Expense | E73: 2026-07-11T23:17:47.702 | F73: 2026-07-11T23:17:47.702 | H73: =IF(O73="","",IFERROR(INDEX(Accounts!$B$2:$B$24,MATCH(O73,Accounts!$A$2:$A$24,0)),"Unknown")) | I73: =IF(P73="","",IFERROR(INDEX(Categories!$B$2:$B$25,MATCH(P73,Categories!$A$2:$A$25,0)),"Unknown")) | J73: =IF(Q73="","",IFERROR(INDEX(Accounts!$B$2:$B$24,MATCH(Q73,Accounts!$A$2:$A$24,0)),"Unknown")) | K73: =IF(R73="","",IFERROR(INDEX(Accounts!$B$2:$B$24,MATCH(R73,Accounts!$A$2:$A$24,0)),"Unknown")) | L73: =IF(S73="","",IFERROR(INDEX(People!$B$2:$B$7,MATCH(S73,People!$A$2:$A$7,0)),"Unknown")) | M73: =IF(T73="","",IFERROR(INDEX(Recurrings!$B$2:$B$3,MATCH(T73,Recurrings!$A$2:$A$3,0)),"Unknown")) | N73: =IF(U73="","",IFERROR(INDEX(Users!$B$2:$B$2,MATCH(U73,Users!$A$2:$A$2,0)),"Unknown")) | O73: b97245b7-cfde-4557-9035-8297edba21af | P73: d1a09f78-95d2-4fb3-9dd1-1ae8a33fa3d8 | U73: 814248de-0f8d-4712-bd00-91d12164a414
A74: 75 | B74: Rent july | C74: 17500 | D74: Expense | E74: 2026-07-12T12:57:01.195 | F74: 2026-07-12T13:03:32.006 | G74: 1000 electricity (13308-13408) meter at 13408 | H74: =IF(O74="","",IFERROR(INDEX(Accounts!$B$2:$B$24,MATCH(O74,Accounts!$A$2:$A$24,0)),"Unknown")) | I74: =IF(P74="","",IFERROR(INDEX(Categories!$B$2:$B$25,MATCH(P74,Categories!$A$2:$A$25,0)),"Unknown")) | J74: =IF(Q74="","",IFERROR(INDEX(Accounts!$B$2:$B$24,MATCH(Q74,Accounts!$A$2:$A$24,0)),"Unknown")) | K74: =IF(R74="","",IFERROR(INDEX(Accounts!$B$2:$B$24,MATCH(R74,Accounts!$A$2:$A$24,0)),"Unknown")) | L74: =IF(S74="","",IFERROR(INDEX(People!$B$2:$B$7,MATCH(S74,People!$A$2:$A$7,0)),"Unknown")) | M74: =IF(T74="","",IFERROR(INDEX(Recurrings!$B$2:$B$3,MATCH(T74,Recurrings!$A$2:$A$3,0)),"Unknown")) | N74: =IF(U74="","",IFERROR(INDEX(Users!$B$2:$B$2,MATCH(U74,Users!$A$2:$A$2,0)),"Unknown")) | O74: 7f7a9ca8-7be5-4ea0-811a-63e598d2c6d3 | P74: 918ebcda-33fa-40b6-848d-95dd00f74bad | U74: 814248de-0f8d-4712-bd00-91d12164a414
A75: 76 | B75: Atm withdrawal | C75: 10000 | D75: Transfer | E75: 2026-07-11T12:59:11.000 | F75: 2026-07-12T13:11:35.987 | H75: =IF(O75="","",IFERROR(INDEX(Accounts!$B$2:$B$24,MATCH(O75,Accounts!$A$2:$A$24,0)),"Unknown")) | I75: =IF(P75="","",IFERROR(INDEX(Categories!$B$2:$B$25,MATCH(P75,Categories!$A$2:$A$25,0)),"Unknown")) | J75: =IF(Q75="","",IFERROR(INDEX(Accounts!$B$2:$B$24,MATCH(Q75,Accounts!$A$2:$A$24,0)),"Unknown")) | K75: =IF(R75="","",IFERROR(INDEX(Accounts!$B$2:$B$24,MATCH(R75,Accounts!$A$2:$A$24,0)),"Unknown")) | L75: =IF(S75="","",IFERROR(INDEX(People!$B$2:$B$7,MATCH(S75,People!$A$2:$A$7,0)),"Unknown")) | M75: =IF(T75="","",IFERROR(INDEX(Recurrings!$B$2:$B$3,MATCH(T75,Recurrings!$A$2:$A$3,0)),"Unknown")) | N75: =IF(U75="","",IFERROR(INDEX(Users!$B$2:$B$2,MATCH(U75,Users!$A$2:$A$2,0)),"Unknown")) | Q75: 2b9af0c9-8855-4666-9be1-4c781d9f1ec3 | R75: 7f7a9ca8-7be5-4ea0-811a-63e598d2c6d3 | U75: 814248de-0f8d-4712-bd00-91d12164a414
A76: 77 | B76: Atm withdrawal | C76: 8000 | D76: Transfer | E76: 2026-07-11T13:02:26.000 | F76: 2026-07-12T13:02:51.147 | H76: =IF(O76="","",IFERROR(INDEX(Accounts!$B$2:$B$24,MATCH(O76,Accounts!$A$2:$A$24,0)),"Unknown")) | I76: =IF(P76="","",IFERROR(INDEX(Categories!$B$2:$B$25,MATCH(P76,Categories!$A$2:$A$25,0)),"Unknown")) | J76: =IF(Q76="","",IFERROR(INDEX(Accounts!$B$2:$B$24,MATCH(Q76,Accounts!$A$2:$A$24,0)),"Unknown")) | K76: =IF(R76="","",IFERROR(INDEX(Accounts!$B$2:$B$24,MATCH(R76,Accounts!$A$2:$A$24,0)),"Unknown")) | L76: =IF(S76="","",IFERROR(INDEX(People!$B$2:$B$7,MATCH(S76,People!$A$2:$A$7,0)),"Unknown")) | M76: =IF(T76="","",IFERROR(INDEX(Recurrings!$B$2:$B$3,MATCH(T76,Recurrings!$A$2:$A$3,0)),"Unknown")) | N76: =IF(U76="","",IFERROR(INDEX(Users!$B$2:$B$2,MATCH(U76,Users!$A$2:$A$2,0)),"Unknown")) | Q76: a5b44f57-40f5-4b0e-96db-1179f20d75d0 | R76: 7f7a9ca8-7be5-4ea0-811a-63e598d2c6d3 | U76: 814248de-0f8d-4712-bd00-91d12164a414
A77: 78 | B77: Wallet | C77: 2430 | D77: Income | E77: 2026-07-12T13:08:27.848 | F77: 2026-07-12T13:08:27.848 | H77: =IF(O77="","",IFERROR(INDEX(Accounts!$B$2:$B$24,MATCH(O77,Accounts!$A$2:$A$24,0)),"Unknown")) | I77: =IF(P77="","",IFERROR(INDEX(Categories!$B$2:$B$25,MATCH(P77,Categories!$A$2:$A$25,0)),"Unknown")) | J77: =IF(Q77="","",IFERROR(INDEX(Accounts!$B$2:$B$24,MATCH(Q77,Accounts!$A$2:$A$24,0)),"Unknown")) | K77: =IF(R77="","",IFERROR(INDEX(Accounts!$B$2:$B$24,MATCH(R77,Accounts!$A$2:$A$24,0)),"Unknown")) | L77: =IF(S77="","",IFERROR(INDEX(People!$B$2:$B$7,MATCH(S77,People!$A$2:$A$7,0)),"Unknown")) | M77: =IF(T77="","",IFERROR(INDEX(Recurrings!$B$2:$B$3,MATCH(T77,Recurrings!$A$2:$A$3,0)),"Unknown")) | N77: =IF(U77="","",IFERROR(INDEX(Users!$B$2:$B$2,MATCH(U77,Users!$A$2:$A$2,0)),"Unknown")) | O77: 7f7a9ca8-7be5-4ea0-811a-63e598d2c6d3 | P77: 1c612037-9067-4e69-aebc-14619b77b363 | U77: 814248de-0f8d-4712-bd00-91d12164a414
A78: 79 | B78: Expense | C78: 180 | D78: Expense | E78: 2026-07-11T13:14:55.000 | F78: 2026-07-31T00:06:10.456 | H78: =IF(O78="","",IFERROR(INDEX(Accounts!$B$2:$B$24,MATCH(O78,Accounts!$A$2:$A$24,0)),"Unknown")) | I78: =IF(P78="","",IFERROR(INDEX(Categories!$B$2:$B$25,MATCH(P78,Categories!$A$2:$A$25,0)),"Unknown")) | J78: =IF(Q78="","",IFERROR(INDEX(Accounts!$B$2:$B$24,MATCH(Q78,Accounts!$A$2:$A$24,0)),"Unknown")) | K78: =IF(R78="","",IFERROR(INDEX(Accounts!$B$2:$B$24,MATCH(R78,Accounts!$A$2:$A$24,0)),"Unknown")) | L78: =IF(S78="","",IFERROR(INDEX(People!$B$2:$B$7,MATCH(S78,People!$A$2:$A$7,0)),"Unknown")) | M78: =IF(T78="","",IFERROR(INDEX(Recurrings!$B$2:$B$3,MATCH(T78,Recurrings!$A$2:$A$3,0)),"Unknown")) | N78: =IF(U78="","",IFERROR(INDEX(Users!$B$2:$B$2,MATCH(U78,Users!$A$2:$A$2,0)),"Unknown")) | O78: 18110823-8fe5-4547-b1d3-8dbd2cc5b2e3 | P78: 892419eb-083b-410f-b146-1f3c70914aa1 | S78: ca7539c0-14da-430a-ae59-44fee8b96222 | U78: 814248de-0f8d-4712-bd00-91d12164a414
A79: 80 | B79: Cover | C79: 100 | D79: Expense | E79: 2026-07-12T20:41:07.575 | F79: 2026-07-12T20:41:07.575 | H79: =IF(O79="","",IFERROR(INDEX(Accounts!$B$2:$B$24,MATCH(O79,Accounts!$A$2:$A$24,0)),"Unknown")) | I79: =IF(P79="","",IFERROR(INDEX(Categories!$B$2:$B$25,MATCH(P79,Categories!$A$2:$A$25,0)),"Unknown")) | J79: =IF(Q79="","",IFERROR(INDEX(Accounts!$B$2:$B$24,MATCH(Q79,Accounts!$A$2:$A$24,0)),"Unknown")) | K79: =IF(R79="","",IFERROR(INDEX(Accounts!$B$2:$B$24,MATCH(R79,Accounts!$A$2:$A$24,0)),"Unknown")) | L79: =IF(S79="","",IFERROR(INDEX(People!$B$2:$B$7,MATCH(S79,People!$A$2:$A$7,0)),"Unknown")) | M79: =IF(T79="","",IFERROR(INDEX(Recurrings!$B$2:$B$3,MATCH(T79,Recurrings!$A$2:$A$3,0)),"Unknown")) | N79: =IF(U79="","",IFERROR(INDEX(Users!$B$2:$B$2,MATCH(U79,Users!$A$2:$A$2,0)),"Unknown")) | O79: 7f7a9ca8-7be5-4ea0-811a-63e598d2c6d3 | P79: d1a09f78-95d2-4fb3-9dd1-1ae8a33fa3d8 | U79: 814248de-0f8d-4712-bd00-91d12164a414
A80: 81 | B80: Chola mix | C80: 30 | D80: Expense | E80: 2026-07-12T20:55:07.408 | F80: 2026-07-12T20:55:07.408 | H80: =IF(O80="","",IFERROR(INDEX(Accounts!$B$2:$B$24,MATCH(O80,Accounts!$A$2:$A$24,0)),"Unknown")) | I80: =IF(P80="","",IFERROR(INDEX(Categories!$B$2:$B$25,MATCH(P80,Categories!$A$2:$A$25,0)),"Unknown")) | J80: =IF(Q80="","",IFERROR(INDEX(Accounts!$B$2:$B$24,MATCH(Q80,Accounts!$A$2:$A$24,0)),"Unknown")) | K80: =IF(R80="","",IFERROR(INDEX(Accounts!$B$2:$B$24,MATCH(R80,Accounts!$A$2:$A$24,0)),"Unknown")) | L80: =IF(S80="","",IFERROR(INDEX(People!$B$2:$B$7,MATCH(S80,People!$A$2:$A$7,0)),"Unknown")) | M80: =IF(T80="","",IFERROR(INDEX(Recurrings!$B$2:$B$3,MATCH(T80,Recurrings!$A$2:$A$3,0)),"Unknown")) | N80: =IF(U80="","",IFERROR(INDEX(Users!$B$2:$B$2,MATCH(U80,Users!$A$2:$A$2,0)),"Unknown")) | O80: 7f7a9ca8-7be5-4ea0-811a-63e598d2c6d3 | P80: 9ea0a2b1-4b22-40a4-81ab-843452f9c274 | U80: 814248de-0f8d-4712-bd00-91d12164a414
A81: 82 | B81: Fruits | C81: 124 | D81: Expense | E81: 2026-07-12T21:00:28.473 | F81: 2026-07-12T21:00:28.473 | H81: =IF(O81="","",IFERROR(INDEX(Accounts!$B$2:$B$24,MATCH(O81,Accounts!$A$2:$A$24,0)),"Unknown")) | I81: =IF(P81="","",IFERROR(INDEX(Categories!$B$2:$B$25,MATCH(P81,Categories!$A$2:$A$25,0)),"Unknown")) | J81: =IF(Q81="","",IFERROR(INDEX(Accounts!$B$2:$B$24,MATCH(Q81,Accounts!$A$2:$A$24,0)),"Unknown")) | K81: =IF(R81="","",IFERROR(INDEX(Accounts!$B$2:$B$24,MATCH(R81,Accounts!$A$2:$A$24,0)),"Unknown")) | L81: =IF(S81="","",IFERROR(INDEX(People!$B$2:$B$7,MATCH(S81,People!$A$2:$A$7,0)),"Unknown")) | M81: =IF(T81="","",IFERROR(INDEX(Recurrings!$B$2:$B$3,MATCH(T81,Recurrings!$A$2:$A$3,0)),"Unknown")) | N81: =IF(U81="","",IFERROR(INDEX(Users!$B$2:$B$2,MATCH(U81,Users!$A$2:$A$2,0)),"Unknown")) | O81: aa69aba3-4e60-426d-adfa-15f984249883 | P81: 066d9d96-53ec-4eb7-a045-fc8dfb1d33cb | U81: 814248de-0f8d-4712-bd00-91d12164a414
A82: 83 | B82: Gmc ke lie diya | C82: 300 | D82: Expense | E82: 2026-07-12T22:23:13.021 | F82: 2026-07-12T22:23:13.021 | G82: C/O Bajrang Jhawar | H82: =IF(O82="","",IFERROR(INDEX(Accounts!$B$2:$B$24,MATCH(O82,Accounts!$A$2:$A$24,0)),"Unknown")) | I82: =IF(P82="","",IFERROR(INDEX(Categories!$B$2:$B$25,MATCH(P82,Categories!$A$2:$A$25,0)),"Unknown")) | J82: =IF(Q82="","",IFERROR(INDEX(Accounts!$B$2:$B$24,MATCH(Q82,Accounts!$A$2:$A$24,0)),"Unknown")) | K82: =IF(R82="","",IFERROR(INDEX(Accounts!$B$2:$B$24,MATCH(R82,Accounts!$A$2:$A$24,0)),"Unknown")) | L82: =IF(S82="","",IFERROR(INDEX(People!$B$2:$B$7,MATCH(S82,People!$A$2:$A$7,0)),"Unknown")) | M82: =IF(T82="","",IFERROR(INDEX(Recurrings!$B$2:$B$3,MATCH(T82,Recurrings!$A$2:$A$3,0)),"Unknown")) | N82: =IF(U82="","",IFERROR(INDEX(Users!$B$2:$B$2,MATCH(U82,Users!$A$2:$A$2,0)),"Unknown")) | O82: a5b44f57-40f5-4b0e-96db-1179f20d75d0 | P82: b5eb22d9-3779-43fc-99af-eded3ff9bcd8 | U82: 814248de-0f8d-4712-bd00-91d12164a414
A83: 84 | B83: Expense | C83: 430 | D83: Expense | E83: 2026-07-12T23:27:45.696 | F83: 2026-07-12T23:27:45.696 | H83: =IF(O83="","",IFERROR(INDEX(Accounts!$B$2:$B$24,MATCH(O83,Accounts!$A$2:$A$24,0)),"Unknown")) | I83: =IF(P83="","",IFERROR(INDEX(Categories!$B$2:$B$25,MATCH(P83,Categories!$A$2:$A$25,0)),"Unknown")) | J83: =IF(Q83="","",IFERROR(INDEX(Accounts!$B$2:$B$24,MATCH(Q83,Accounts!$A$2:$A$24,0)),"Unknown")) | K83: =IF(R83="","",IFERROR(INDEX(Accounts!$B$2:$B$24,MATCH(R83,Accounts!$A$2:$A$24,0)),"Unknown")) | L83: =IF(S83="","",IFERROR(INDEX(People!$B$2:$B$7,MATCH(S83,People!$A$2:$A$7,0)),"Unknown")) | M83: =IF(T83="","",IFERROR(INDEX(Recurrings!$B$2:$B$3,MATCH(T83,Recurrings!$A$2:$A$3,0)),"Unknown")) | N83: =IF(U83="","",IFERROR(INDEX(Users!$B$2:$B$2,MATCH(U83,Users!$A$2:$A$2,0)),"Unknown")) | O83: 183283c7-9ae3-49e4-ae84-a5364bc337ea | P83: 892419eb-083b-410f-b146-1f3c70914aa1 | S83: 7214a9a0-5619-49f8-8521-181d4faf1190 | U83: 814248de-0f8d-4712-bd00-91d12164a414
A84: 85 | B84: Expense | C84: 10 | D84: Expense | E84: 2026-07-12T23:28:01.339 | F84: 2026-07-12T23:28:01.339 | H84: =IF(O84="","",IFERROR(INDEX(Accounts!$B$2:$B$24,MATCH(O84,Accounts!$A$2:$A$24,0)),"Unknown")) | I84: =IF(P84="","",IFERROR(INDEX(Categories!$B$2:$B$25,MATCH(P84,Categories!$A$2:$A$25,0)),"Unknown")) | J84: =IF(Q84="","",IFERROR(INDEX(Accounts!$B$2:$B$24,MATCH(Q84,Accounts!$A$2:$A$24,0)),"Unknown")) | K84: =IF(R84="","",IFERROR(INDEX(Accounts!$B$2:$B$24,MATCH(R84,Accounts!$A$2:$A$24,0)),"Unknown")) | L84: =IF(S84="","",IFERROR(INDEX(People!$B$2:$B$7,MATCH(S84,People!$A$2:$A$7,0)),"Unknown")) | M84: =IF(T84="","",IFERROR(INDEX(Recurrings!$B$2:$B$3,MATCH(T84,Recurrings!$A$2:$A$3,0)),"Unknown")) | N84: =IF(U84="","",IFERROR(INDEX(Users!$B$2:$B$2,MATCH(U84,Users!$A$2:$A$2,0)),"Unknown")) | O84: 8cedd8c1-7bcb-4b94-be6b-e72b888f1084 | P84: 892419eb-083b-410f-b146-1f3c70914aa1 | S84: 7214a9a0-5619-49f8-8521-181d4faf1190 | U84: 814248de-0f8d-4712-bd00-91d12164a414
A85: 86 | B85: Refund for pixel 10 case | C85: 2205 | D85: Income | E85: 2026-07-13T00:51:34.974 | F85: 2026-07-13T00:51:34.974 | H85: =IF(O85="","",IFERROR(INDEX(Accounts!$B$2:$B$24,MATCH(O85,Accounts!$A$2:$A$24,0)),"Unknown")) | I85: =IF(P85="","",IFERROR(INDEX(Categories!$B$2:$B$25,MATCH(P85,Categories!$A$2:$A$25,0)),"Unknown")) | J85: =IF(Q85="","",IFERROR(INDEX(Accounts!$B$2:$B$24,MATCH(Q85,Accounts!$A$2:$A$24,0)),"Unknown")) | K85: =IF(R85="","",IFERROR(INDEX(Accounts!$B$2:$B$24,MATCH(R85,Accounts!$A$2:$A$24,0)),"Unknown")) | L85: =IF(S85="","",IFERROR(INDEX(People!$B$2:$B$7,MATCH(S85,People!$A$2:$A$7,0)),"Unknown")) | M85: =IF(T85="","",IFERROR(INDEX(Recurrings!$B$2:$B$3,MATCH(T85,Recurrings!$A$2:$A$3,0)),"Unknown")) | N85: =IF(U85="","",IFERROR(INDEX(Users!$B$2:$B$2,MATCH(U85,Users!$A$2:$A$2,0)),"Unknown")) | O85: 88892af2-1b81-4798-904f-38a863b1aa57 | P85: 1c612037-9067-4e69-aebc-14619b77b363 | U85: 814248de-0f8d-4712-bd00-91d12164a414
A86: 87 | B86: Cashback | C86: 29 | D86: Income | E86: 2026-07-01T00:51:47.000 | F86: 2026-07-13T00:52:08.550 | H86: =IF(O86="","",IFERROR(INDEX(Accounts!$B$2:$B$24,MATCH(O86,Accounts!$A$2:$A$24,0)),"Unknown")) | I86: =IF(P86="","",IFERROR(INDEX(Categories!$B$2:$B$25,MATCH(P86,Categories!$A$2:$A$25,0)),"Unknown")) | J86: =IF(Q86="","",IFERROR(INDEX(Accounts!$B$2:$B$24,MATCH(Q86,Accounts!$A$2:$A$24,0)),"Unknown")) | K86: =IF(R86="","",IFERROR(INDEX(Accounts!$B$2:$B$24,MATCH(R86,Accounts!$A$2:$A$24,0)),"Unknown")) | L86: =IF(S86="","",IFERROR(INDEX(People!$B$2:$B$7,MATCH(S86,People!$A$2:$A$7,0)),"Unknown")) | M86: =IF(T86="","",IFERROR(INDEX(Recurrings!$B$2:$B$3,MATCH(T86,Recurrings!$A$2:$A$3,0)),"Unknown")) | N86: =IF(U86="","",IFERROR(INDEX(Users!$B$2:$B$2,MATCH(U86,Users!$A$2:$A$2,0)),"Unknown")) | O86: 88892af2-1b81-4798-904f-38a863b1aa57 | P86: 1c612037-9067-4e69-aebc-14619b77b363 | U86: 814248de-0f8d-4712-bd00-91d12164a414
A87: 88 | B87: Water | C87: 50 | D87: Expense | E87: 2026-07-13T10:10:43.873 | F87: 2026-07-13T10:10:43.873 | H87: =IF(O87="","",IFERROR(INDEX(Accounts!$B$2:$B$24,MATCH(O87,Accounts!$A$2:$A$24,0)),"Unknown")) | I87: =IF(P87="","",IFERROR(INDEX(Categories!$B$2:$B$25,MATCH(P87,Categories!$A$2:$A$25,0)),"Unknown")) | J87: =IF(Q87="","",IFERROR(INDEX(Accounts!$B$2:$B$24,MATCH(Q87,Accounts!$A$2:$A$24,0)),"Unknown")) | K87: =IF(R87="","",IFERROR(INDEX(Accounts!$B$2:$B$24,MATCH(R87,Accounts!$A$2:$A$24,0)),"Unknown")) | L87: =IF(S87="","",IFERROR(INDEX(People!$B$2:$B$7,MATCH(S87,People!$A$2:$A$7,0)),"Unknown")) | M87: =IF(T87="","",IFERROR(INDEX(Recurrings!$B$2:$B$3,MATCH(T87,Recurrings!$A$2:$A$3,0)),"Unknown")) | N87: =IF(U87="","",IFERROR(INDEX(Users!$B$2:$B$2,MATCH(U87,Users!$A$2:$A$2,0)),"Unknown")) | O87: a5b44f57-40f5-4b0e-96db-1179f20d75d0 | P87: 6a1261ca-46ca-4428-a67a-c5653840e2e9 | U87: 814248de-0f8d-4712-bd00-91d12164a414
A88: 89 | B88: Lunch | C88: 101 | D88: Expense | E88: 2026-07-13T13:32:51.441 | F88: 2026-07-13T13:32:51.441 | H88: =IF(O88="","",IFERROR(INDEX(Accounts!$B$2:$B$24,MATCH(O88,Accounts!$A$2:$A$24,0)),"Unknown")) | I88: =IF(P88="","",IFERROR(INDEX(Categories!$B$2:$B$25,MATCH(P88,Categories!$A$2:$A$25,0)),"Unknown")) | J88: =IF(Q88="","",IFERROR(INDEX(Accounts!$B$2:$B$24,MATCH(Q88,Accounts!$A$2:$A$24,0)),"Unknown")) | K88: =IF(R88="","",IFERROR(INDEX(Accounts!$B$2:$B$24,MATCH(R88,Accounts!$A$2:$A$24,0)),"Unknown")) | L88: =IF(S88="","",IFERROR(INDEX(People!$B$2:$B$7,MATCH(S88,People!$A$2:$A$7,0)),"Unknown")) | M88: =IF(T88="","",IFERROR(INDEX(Recurrings!$B$2:$B$3,MATCH(T88,Recurrings!$A$2:$A$3,0)),"Unknown")) | N88: =IF(U88="","",IFERROR(INDEX(Users!$B$2:$B$2,MATCH(U88,Users!$A$2:$A$2,0)),"Unknown")) | O88: aa69aba3-4e60-426d-adfa-15f984249883 | P88: 9ea0a2b1-4b22-40a4-81ab-843452f9c274 | U88: 814248de-0f8d-4712-bd00-91d12164a414
A89: 90 | B89: Office fare | C89: 27 | D89: Expense | E89: 2026-07-13T20:04:09.965 | F89: 2026-07-13T20:04:09.965 | H89: =IF(O89="","",IFERROR(INDEX(Accounts!$B$2:$B$24,MATCH(O89,Accounts!$A$2:$A$24,0)),"Unknown")) | I89: =IF(P89="","",IFERROR(INDEX(Categories!$B$2:$B$25,MATCH(P89,Categories!$A$2:$A$25,0)),"Unknown")) | J89: =IF(Q89="","",IFERROR(INDEX(Accounts!$B$2:$B$24,MATCH(Q89,Accounts!$A$2:$A$24,0)),"Unknown")) | K89: =IF(R89="","",IFERROR(INDEX(Accounts!$B$2:$B$24,MATCH(R89,Accounts!$A$2:$A$24,0)),"Unknown")) | L89: =IF(S89="","",IFERROR(INDEX(People!$B$2:$B$7,MATCH(S89,People!$A$2:$A$7,0)),"Unknown")) | M89: =IF(T89="","",IFERROR(INDEX(Recurrings!$B$2:$B$3,MATCH(T89,Recurrings!$A$2:$A$3,0)),"Unknown")) | N89: =IF(U89="","",IFERROR(INDEX(Users!$B$2:$B$2,MATCH(U89,Users!$A$2:$A$2,0)),"Unknown")) | O89: 7f7a9ca8-7be5-4ea0-811a-63e598d2c6d3 | P89: 59cb1d7a-195c-4fef-b7e6-682eb97de8a7 | U89: 814248de-0f8d-4712-bd00-91d12164a414
A90: 91 | B90: Office Transport Leverage | C90: 200 | D90: Income | E90: 2026-07-13T20:44:45.223 | F90: 2026-07-13T20:04:45.638 | H90: =IF(O90="","",IFERROR(INDEX(Accounts!$B$2:$B$24,MATCH(O90,Accounts!$A$2:$A$24,0)),"Unknown")) | I90: =IF(P90="","",IFERROR(INDEX(Categories!$B$2:$B$25,MATCH(P90,Categories!$A$2:$A$25,0)),"Unknown")) | J90: =IF(Q90="","",IFERROR(INDEX(Accounts!$B$2:$B$24,MATCH(Q90,Accounts!$A$2:$A$24,0)),"Unknown")) | K90: =IF(R90="","",IFERROR(INDEX(Accounts!$B$2:$B$24,MATCH(R90,Accounts!$A$2:$A$24,0)),"Unknown")) | L90: =IF(S90="","",IFERROR(INDEX(People!$B$2:$B$7,MATCH(S90,People!$A$2:$A$7,0)),"Unknown")) | M90: =IF(T90="","",IFERROR(INDEX(Recurrings!$B$2:$B$3,MATCH(T90,Recurrings!$A$2:$A$3,0)),"Unknown")) | N90: =IF(U90="","",IFERROR(INDEX(Users!$B$2:$B$2,MATCH(U90,Users!$A$2:$A$2,0)),"Unknown")) | O90: f89518bd-b7d1-4658-9692-994af79cfcb8 | P90: f894a6a7-dfc4-4c79-bf71-b2526dc474ac | T90: 5f717740-b341-4fec-9dee-eb1c70d3c260 | U90: 814248de-0f8d-4712-bd00-91d12164a414
A91: 92 | B91: Expense | C91: 260 | D91: Expense | E91: 2026-07-13T23:39:10.381 | F91: 2026-07-13T23:39:10.381 | H91: =IF(O91="","",IFERROR(INDEX(Accounts!$B$2:$B$24,MATCH(O91,Accounts!$A$2:$A$24,0)),"Unknown")) | I91: =IF(P91="","",IFERROR(INDEX(Categories!$B$2:$B$25,MATCH(P91,Categories!$A$2:$A$25,0)),"Unknown")) | J91: =IF(Q91="","",IFERROR(INDEX(Accounts!$B$2:$B$24,MATCH(Q91,Accounts!$A$2:$A$24,0)),"Unknown")) | K91: =IF(R91="","",IFERROR(INDEX(Accounts!$B$2:$B$24,MATCH(R91,Accounts!$A$2:$A$24,0)),"Unknown")) | L91: =IF(S91="","",IFERROR(INDEX(People!$B$2:$B$7,MATCH(S91,People!$A$2:$A$7,0)),"Unknown")) | M91: =IF(T91="","",IFERROR(INDEX(Recurrings!$B$2:$B$3,MATCH(T91,Recurrings!$A$2:$A$3,0)),"Unknown")) | N91: =IF(U91="","",IFERROR(INDEX(Users!$B$2:$B$2,MATCH(U91,Users!$A$2:$A$2,0)),"Unknown")) | O91: 8cedd8c1-7bcb-4b94-be6b-e72b888f1084 | P91: 892419eb-083b-410f-b146-1f3c70914aa1 | S91: 7214a9a0-5619-49f8-8521-181d4faf1190 | U91: 814248de-0f8d-4712-bd00-91d12164a414
A92: 93 | B92: Expense | C92: 260 | D92: Expense | E92: 2026-07-13T23:39:42.726 | F92: 2026-07-13T23:39:42.726 | H92: =IF(O92="","",IFERROR(INDEX(Accounts!$B$2:$B$24,MATCH(O92,Accounts!$A$2:$A$24,0)),"Unknown")) | I92: =IF(P92="","",IFERROR(INDEX(Categories!$B$2:$B$25,MATCH(P92,Categories!$A$2:$A$25,0)),"Unknown")) | J92: =IF(Q92="","",IFERROR(INDEX(Accounts!$B$2:$B$24,MATCH(Q92,Accounts!$A$2:$A$24,0)),"Unknown")) | K92: =IF(R92="","",IFERROR(INDEX(Accounts!$B$2:$B$24,MATCH(R92,Accounts!$A$2:$A$24,0)),"Unknown")) | L92: =IF(S92="","",IFERROR(INDEX(People!$B$2:$B$7,MATCH(S92,People!$A$2:$A$7,0)),"Unknown")) | M92: =IF(T92="","",IFERROR(INDEX(Recurrings!$B$2:$B$3,MATCH(T92,Recurrings!$A$2:$A$3,0)),"Unknown")) | N92: =IF(U92="","",IFERROR(INDEX(Users!$B$2:$B$2,MATCH(U92,Users!$A$2:$A$2,0)),"Unknown")) | O92: 183283c7-9ae3-49e4-ae84-a5364bc337ea | P92: 892419eb-083b-410f-b146-1f3c70914aa1 | S92: 7214a9a0-5619-49f8-8521-181d4faf1190 | U92: 814248de-0f8d-4712-bd00-91d12164a414
A93: 94 | B93: Expense | C93: 55 | D93: Expense | E93: 2026-07-13T20:45:14.000 | F93: 2026-07-14T00:09:57.150 | H93: =IF(O93="","",IFERROR(INDEX(Accounts!$B$2:$B$24,MATCH(O93,Accounts!$A$2:$A$24,0)),"Unknown")) | I93: =IF(P93="","",IFERROR(INDEX(Categories!$B$2:$B$25,MATCH(P93,Categories!$A$2:$A$25,0)),"Unknown")) | J93: =IF(Q93="","",IFERROR(INDEX(Accounts!$B$2:$B$24,MATCH(Q93,Accounts!$A$2:$A$24,0)),"Unknown")) | K93: =IF(R93="","",IFERROR(INDEX(Accounts!$B$2:$B$24,MATCH(R93,Accounts!$A$2:$A$24,0)),"Unknown")) | L93: =IF(S93="","",IFERROR(INDEX(People!$B$2:$B$7,MATCH(S93,People!$A$2:$A$7,0)),"Unknown")) | M93: =IF(T93="","",IFERROR(INDEX(Recurrings!$B$2:$B$3,MATCH(T93,Recurrings!$A$2:$A$3,0)),"Unknown")) | N93: =IF(U93="","",IFERROR(INDEX(Users!$B$2:$B$2,MATCH(U93,Users!$A$2:$A$2,0)),"Unknown")) | O93: 18110823-8fe5-4547-b1d3-8dbd2cc5b2e3 | P93: 892419eb-083b-410f-b146-1f3c70914aa1 | S93: ca7539c0-14da-430a-ae59-44fee8b96222 | U93: 814248de-0f8d-4712-bd00-91d12164a414
A94: 95 | B94: Credit for bill | C94: 34770.82 | D94: Transfer | E94: 2026-07-14T19:20:49.450 | F94: 2026-07-14T19:20:49.450 | H94: =IF(O94="","",IFERROR(INDEX(Accounts!$B$2:$B$24,MATCH(O94,Accounts!$A$2:$A$24,0)),"Unknown")) | I94: =IF(P94="","",IFERROR(INDEX(Categories!$B$2:$B$25,MATCH(P94,Categories!$A$2:$A$25,0)),"Unknown")) | J94: =IF(Q94="","",IFERROR(INDEX(Accounts!$B$2:$B$24,MATCH(Q94,Accounts!$A$2:$A$24,0)),"Unknown")) | K94: =IF(R94="","",IFERROR(INDEX(Accounts!$B$2:$B$24,MATCH(R94,Accounts!$A$2:$A$24,0)),"Unknown")) | L94: =IF(S94="","",IFERROR(INDEX(People!$B$2:$B$7,MATCH(S94,People!$A$2:$A$7,0)),"Unknown")) | M94: =IF(T94="","",IFERROR(INDEX(Recurrings!$B$2:$B$3,MATCH(T94,Recurrings!$A$2:$A$3,0)),"Unknown")) | N94: =IF(U94="","",IFERROR(INDEX(Users!$B$2:$B$2,MATCH(U94,Users!$A$2:$A$2,0)),"Unknown")) | Q94: 2b9af0c9-8855-4666-9be1-4c781d9f1ec3 | R94: aa69aba3-4e60-426d-adfa-15f984249883 | U94: 814248de-0f8d-4712-bd00-91d12164a414
A95: 96 | B95: Gold payment mom | C95: 30000 | D95: Expense | E95: 2026-07-14T19:21:12.642 | F95: 2026-07-14T19:21:12.642 | H95: =IF(O95="","",IFERROR(INDEX(Accounts!$B$2:$B$24,MATCH(O95,Accounts!$A$2:$A$24,0)),"Unknown")) | I95: =IF(P95="","",IFERROR(INDEX(Categories!$B$2:$B$25,MATCH(P95,Categories!$A$2:$A$25,0)),"Unknown")) | J95: =IF(Q95="","",IFERROR(INDEX(Accounts!$B$2:$B$24,MATCH(Q95,Accounts!$A$2:$A$24,0)),"Unknown")) | K95: =IF(R95="","",IFERROR(INDEX(Accounts!$B$2:$B$24,MATCH(R95,Accounts!$A$2:$A$24,0)),"Unknown")) | L95: =IF(S95="","",IFERROR(INDEX(People!$B$2:$B$7,MATCH(S95,People!$A$2:$A$7,0)),"Unknown")) | M95: =IF(T95="","",IFERROR(INDEX(Recurrings!$B$2:$B$3,MATCH(T95,Recurrings!$A$2:$A$3,0)),"Unknown")) | N95: =IF(U95="","",IFERROR(INDEX(Users!$B$2:$B$2,MATCH(U95,Users!$A$2:$A$2,0)),"Unknown")) | O95: aa69aba3-4e60-426d-adfa-15f984249883 | P95: d4addfc4-44b5-4628-8237-9afb254f475b | U95: 814248de-0f8d-4712-bd00-91d12164a414
A96: 97 | B96: Office fare | C96: 27 | D96: Expense | E96: 2026-07-14T19:21:31.456 | F96: 2026-07-14T19:21:31.456 | H96: =IF(O96="","",IFERROR(INDEX(Accounts!$B$2:$B$24,MATCH(O96,Accounts!$A$2:$A$24,0)),"Unknown")) | I96: =IF(P96="","",IFERROR(INDEX(Categories!$B$2:$B$25,MATCH(P96,Categories!$A$2:$A$25,0)),"Unknown")) | J96: =IF(Q96="","",IFERROR(INDEX(Accounts!$B$2:$B$24,MATCH(Q96,Accounts!$A$2:$A$24,0)),"Unknown")) | K96: =IF(R96="","",IFERROR(INDEX(Accounts!$B$2:$B$24,MATCH(R96,Accounts!$A$2:$A$24,0)),"Unknown")) | L96: =IF(S96="","",IFERROR(INDEX(People!$B$2:$B$7,MATCH(S96,People!$A$2:$A$7,0)),"Unknown")) | M96: =IF(T96="","",IFERROR(INDEX(Recurrings!$B$2:$B$3,MATCH(T96,Recurrings!$A$2:$A$3,0)),"Unknown")) | N96: =IF(U96="","",IFERROR(INDEX(Users!$B$2:$B$2,MATCH(U96,Users!$A$2:$A$2,0)),"Unknown")) | O96: 7f7a9ca8-7be5-4ea0-811a-63e598d2c6d3 | P96: 59cb1d7a-195c-4fef-b7e6-682eb97de8a7 | U96: 814248de-0f8d-4712-bd00-91d12164a414
A97: 98 | B97: Ganna juice | C97: 40 | D97: Expense | E97: 2026-07-14T19:21:50.288 | F97: 2026-07-14T19:21:50.288 | H97: =IF(O97="","",IFERROR(INDEX(Accounts!$B$2:$B$24,MATCH(O97,Accounts!$A$2:$A$24,0)),"Unknown")) | I97: =IF(P97="","",IFERROR(INDEX(Categories!$B$2:$B$25,MATCH(P97,Categories!$A$2:$A$25,0)),"Unknown")) | J97: =IF(Q97="","",IFERROR(INDEX(Accounts!$B$2:$B$24,MATCH(Q97,Accounts!$A$2:$A$24,0)),"Unknown")) | K97: =IF(R97="","",IFERROR(INDEX(Accounts!$B$2:$B$24,MATCH(R97,Accounts!$A$2:$A$24,0)),"Unknown")) | L97: =IF(S97="","",IFERROR(INDEX(People!$B$2:$B$7,MATCH(S97,People!$A$2:$A$7,0)),"Unknown")) | M97: =IF(T97="","",IFERROR(INDEX(Recurrings!$B$2:$B$3,MATCH(T97,Recurrings!$A$2:$A$3,0)),"Unknown")) | N97: =IF(U97="","",IFERROR(INDEX(Users!$B$2:$B$2,MATCH(U97,Users!$A$2:$A$2,0)),"Unknown")) | O97: 7f7a9ca8-7be5-4ea0-811a-63e598d2c6d3 | P97: 9ea0a2b1-4b22-40a4-81ab-843452f9c274 | U97: 814248de-0f8d-4712-bd00-91d12164a414
A98: 99 | B98: Milk | C98: 30 | D98: Expense | E98: 2026-07-14T19:22:36.602 | F98: 2026-07-14T19:22:36.602 | H98: =IF(O98="","",IFERROR(INDEX(Accounts!$B$2:$B$24,MATCH(O98,Accounts!$A$2:$A$24,0)),"Unknown")) | I98: =IF(P98="","",IFERROR(INDEX(Categories!$B$2:$B$25,MATCH(P98,Categories!$A$2:$A$25,0)),"Unknown")) | J98: =IF(Q98="","",IFERROR(INDEX(Accounts!$B$2:$B$24,MATCH(Q98,Accounts!$A$2:$A$24,0)),"Unknown")) | K98: =IF(R98="","",IFERROR(INDEX(Accounts!$B$2:$B$24,MATCH(R98,Accounts!$A$2:$A$24,0)),"Unknown")) | L98: =IF(S98="","",IFERROR(INDEX(People!$B$2:$B$7,MATCH(S98,People!$A$2:$A$7,0)),"Unknown")) | M98: =IF(T98="","",IFERROR(INDEX(Recurrings!$B$2:$B$3,MATCH(T98,Recurrings!$A$2:$A$3,0)),"Unknown")) | N98: =IF(U98="","",IFERROR(INDEX(Users!$B$2:$B$2,MATCH(U98,Users!$A$2:$A$2,0)),"Unknown")) | O98: 7f7a9ca8-7be5-4ea0-811a-63e598d2c6d3 | P98: 066d9d96-53ec-4eb7-a045-fc8dfb1d33cb | U98: 814248de-0f8d-4712-bd00-91d12164a414
A99: 100 | B99: Credit for bill | C99: 4565 | D99: Transfer | E99: 2026-07-14T19:24:03.487 | F99: 2026-07-14T19:24:03.487 | H99: =IF(O99="","",IFERROR(INDEX(Accounts!$B$2:$B$24,MATCH(O99,Accounts!$A$2:$A$24,0)),"Unknown")) | I99: =IF(P99="","",IFERROR(INDEX(Categories!$B$2:$B$25,MATCH(P99,Categories!$A$2:$A$25,0)),"Unknown")) | J99: =IF(Q99="","",IFERROR(INDEX(Accounts!$B$2:$B$24,MATCH(Q99,Accounts!$A$2:$A$24,0)),"Unknown")) | K99: =IF(R99="","",IFERROR(INDEX(Accounts!$B$2:$B$24,MATCH(R99,Accounts!$A$2:$A$24,0)),"Unknown")) | L99: =IF(S99="","",IFERROR(INDEX(People!$B$2:$B$7,MATCH(S99,People!$A$2:$A$7,0)),"Unknown")) | M99: =IF(T99="","",IFERROR(INDEX(Recurrings!$B$2:$B$3,MATCH(T99,Recurrings!$A$2:$A$3,0)),"Unknown")) | N99: =IF(U99="","",IFERROR(INDEX(Users!$B$2:$B$2,MATCH(U99,Users!$A$2:$A$2,0)),"Unknown")) | Q99: 2b9af0c9-8855-4666-9be1-4c781d9f1ec3 | R99: dae4882a-382f-4486-ac91-4ce4bafafe34 | U99: 814248de-0f8d-4712-bd00-91d12164a414
A100: 101 | B100: Credit | C100: 4565 | D100: Expense | E100: 2026-07-01T19:24:24.000 | F100: 2026-07-14T19:24:44.834 | H100: =IF(O100="","",IFERROR(INDEX(Accounts!$B$2:$B$24,MATCH(O100,Accounts!$A$2:$A$24,0)),"Unknown")) | I100: =IF(P100="","",IFERROR(INDEX(Categories!$B$2:$B$25,MATCH(P100,Categories!$A$2:$A$25,0)),"Unknown")) | J100: =IF(Q100="","",IFERROR(INDEX(Accounts!$B$2:$B$24,MATCH(Q100,Accounts!$A$2:$A$24,0)),"Unknown")) | K100: =IF(R100="","",IFERROR(INDEX(Accounts!$B$2:$B$24,MATCH(R100,Accounts!$A$2:$A$24,0)),"Unknown")) | L100: =IF(S100="","",IFERROR(INDEX(People!$B$2:$B$7,MATCH(S100,People!$A$2:$A$7,0)),"Unknown")) | M100: =IF(T100="","",IFERROR(INDEX(Recurrings!$B$2:$B$3,MATCH(T100,Recurrings!$A$2:$A$3,0)),"Unknown")) | N100: =IF(U100="","",IFERROR(INDEX(Users!$B$2:$B$2,MATCH(U100,Users!$A$2:$A$2,0)),"Unknown")) | O100: dae4882a-382f-4486-ac91-4ce4bafafe34 | P100: 892419eb-083b-410f-b146-1f3c70914aa1 | U100: 814248de-0f8d-4712-bd00-91d12164a414
...

Sheet Accounts
A1: UUID | B1: Account Name | C1: Bank Name | D1: Account Type | E1: Currency Code | F1: Balance | G1: Is Default | H1: Is Excluded
A2: a5b44f57-40f5-4b0e-96db-1179f20d75d0 | B2: Axis Bank Salary Gautam Saha | C2: Gautam Axis Bank | D2: Cash | F2: 0 | G2: No | H2: No
A3: 7f7a9ca8-7be5-4ea0-811a-63e598d2c6d3 | B3: Gautam Cash | C3: Cash | D3: Card | F3: 0 | G3: No | H3: No
A4: 183283c7-9ae3-49e4-ae84-a5364bc337ea | B4: Dipali Saha Bandhan Bank SB | C4: Bandhan Bank Dipali | D4: Bank Account | F4: 30000 | G4: No | H4: No
A5: e4446497-b2a1-4493-a796-44893af13f78 | B5: Dipen Chandra Saha Bandhan Bank SB | C5: Bandhan Bank Dipen | D5: Bank Account | F5: 0 | G5: No | H5: No
A6: 07510728-f320-4be7-b92d-39526c02e73d | B6: Gautam Chandra Saha Bandhan Bank SB | C6: Bandhan Bank Gautam | D6: Bank Account | F6: 0 | G6: No | H6: No
A7: 6b8aeda1-8500-4f9c-996c-55ad6f6d1bf3 | B7: Dipali Devi Saha Elite | C7: Bandhan Bank Elite | D7: Bank Account | F7: 12874421 | G7: No | H7: No
A8: 641abbfc-3036-49d3-9ffa-8dfcf749f46e | B8: All Accounts Bandhan Bank | C8: Bandhan Bank | D8: Bank Account | F8: 0 | G8: No | H8: No
A9: 18110823-8fe5-4547-b1d3-8dbd2cc5b2e3 | B9: State Bank Of India Dipen | C9: State Bank Of India Dipen | D9: Bank Account | F9: 0 | G9: No | H9: No
A10: 8cedd8c1-7bcb-4b94-be6b-e72b888f1084 | B10: Daily Ghar Kharcha Cash | C10: Cash Home | D10: Card | F10: 0 | G10: No | H10: No
A11: 2b9af0c9-8855-4666-9be1-4c781d9f1ec3 | B11: IDFC bank Gautam | C11: IDFC bank Gautam | D11: Bank Account | F11: 0 | G11: No | H11: No
A12: 4b9fa03c-eddf-42ff-8d5f-eaa9e3086ce0 | B12: Union Bank Gautam | C12: Union Bank Gautam | D12: Bank Account | F12: 11147 | G12: No | H12: No
A13: f89518bd-b7d1-4658-9692-994af79cfcb8 | B13: Office Transport Perks | C13: Office Transport Perk | D13: Card | F13: 0 | G13: No | H13: No
... A24: 79affae5-0d49-47c0-887f-c87bff8f886e | B24: Dumping Account For Recon | C24: Dump Account | D24: Bank Account | F24: 0 | G24: No | H24: No

Sheet Categories
A1: UUID | B1: Category Name | C1: Category Kind | D1: Description
A2: 650e8aa0-fa64-4d3b-8aea-4a5a8cda0750 | B2: Salary | C2: Income
A3: f894a6a7-dfc4-4c79-bf71-b2526dc474ac | B3: Business | C3: Income
A4: f3c3e6df-f387-4860-b6dd-067f4574003c | B4: Gifts | C4: Income
A5: 1593bae6-402a-4f21-b61b-ced2466e51f3 | B5: Investments | C5: Income
A6: 1c612037-9067-4e69-aebc-14619b77b363 | B6: Savings | C6: Income
A7: 892419eb-083b-410f-b146-1f3c70914aa1 | B7: Bills | C7: Expense
A8: 918ebcda-33fa-40b6-848d-95dd00f74bad | B8: Rent | C8: Expense
A9: b2894a89-04c7-4991-af5f-589debb52e30 | B9: Travel | C9: Expense
A10: 9ea0a2b1-4b22-40a4-81ab-843452f9c274 | B10: Food | C10: Expense
A11: 59cb1d7a-195c-4fef-b7e6-682eb97de8a7 | B11: Transport | C11: Expense
A12: d1a09f78-95d2-4fb3-9dd1-1ae8a33fa3d8 | B12: Shopping | C12: Expense
A13: 3ae7db0e-10d1-4fd7-b789-3ec1930fa321 | B13: Entertainment | C13: Expense
... A25: e437a0b5-5f69-4f5b-b879-b8de520215cc | B25: Perk | C25: Income

Sheet People
A1: UUID | B1: Person Name | C1: Description
A2: 7214a9a0-5619-49f8-8521-181d4faf1190 | B2: Dipali
A3: ca7539c0-14da-430a-ae59-44fee8b96222 | B3: Dipen
A4: a86797b7-3cdf-415f-b4ea-16b33ec6d09d | B4: avijitm
A5: e4d7649a-60df-4f0e-a26f-923f8c156122 | B5: nakuln
A6: c2924423-e15e-4e4a-991e-22ad8a4994d2 | B6: jagadiss
A7: 8dae8d46-a8ba-4bb7-af66-0b6bf785eb6f | B7: Gautam

Sheet Users
A1: UUID | B1: User Name | C1: Currency
A2: 814248de-0f8d-4712-bd00-91d12164a414 | B2: Gautam | C2: INR

Sheet Recurrings
A1: UUID | B1: Recurring Name | C1: Period
A2: c893b300-6371-4ec2-b676-904a53f5443f | B2: Spotify premium | C2: 3
A3: 5f717740-b341-4fec-9dee-eb1c70d3c260 | B3: Office Transport Leverage | C3: 0
